Workbook

Sheet mögliche Struktur
A1: öffentlicher Leistungskatalog | I1: Quelleninformation zum internen Gebrauch
N2: in EBM Kalkulationszeit | O2: in EBM Prüfzeit
A3: RM ID | B3: DA | C3: Abschnitt | D3: Unterabschnitt | E3: Leistung | F3: Wert | G3: Bezugsgröße | H3: Bestimmungen | I3: Quelle | J3: Quellenabschnitt | K3: Quellenunterabschnitt | L3: QuellenID | M3: QuellenLeistung | N3: Quellenwert 1 | O3: Quellenwert 2 | P3: Bemerkung
B4: ÄD | I4: GOÄ (GOB) | J4: ='GOÄ-ÄD'!F2 -> B. Grundleistungen und allgemeine Leistungen | K4: ='GOÄ-ÄD'!G2 -> I. Allgemeine Beratungen und Untersuchungen | L4: ='GOÄ-ÄD'!A2 -> 2 | M4: ='GOÄ-ÄD'!B2 -> Ausstellung von Wiederholungsrezepten und/oder Überweisungen | N4: ='GOÄ-ÄD'!C2 -> 2 | P4: ='GOÄ-ÄD'!I2 -> 0
B5: ÄD | I5: GOÄ (GOB) | J5: ='GOÄ-ÄD'!F3 -> B. Grundleistungen und allgemeine Leistungen | K5: ='GOÄ-ÄD'!G3 -> I. Allgemeine Beratungen und Untersuchungen | L5: ='GOÄ-ÄD'!A3 -> 3 | M5: ='GOÄ-ÄD'!B3 -> Eingehende, das gewöhnliche Maß übersteigende Beratung | N5: ='GOÄ-ÄD'!C3 -> 12 | P5: ='GOÄ-ÄD'!I3 -> 0
B6: ÄD | I6: GOÄ (GOB) | J6: ='GOÄ-ÄD'!F4 -> B. Grundleistungen und allgemeine Leistungen | K6: ='GOÄ-ÄD'!G4 -> I. Allgemeine Beratungen und Untersuchungen | L6: ='GOÄ-ÄD'!A4 -> 4 | M6: ='GOÄ-ÄD'!B4 -> Erhebung der Fremdanamnese über einen Kranken | N6: ='GOÄ-ÄD'!C4 -> 14 | P6: ='GOÄ-ÄD'!I4 -> 0
B7: ÄD | I7: GOÄ (GOB) | J7: ='GOÄ-ÄD'!F5 -> B. Grundleistungen und allgemeine Leistungen | K7: ='GOÄ-ÄD'!G5 -> I. Allgemeine Beratungen und Untersuchungen | L7: ='GOÄ-ÄD'!A5 -> 5 | M7: ='GOÄ-ÄD'!B5 -> Ambulante Untersuchung | N7: ='GOÄ-ÄD'!C5 -> 15 | P7: ='GOÄ-ÄD'!I5 -> 0
B8: ÄD | I8: GOÄ (GOB) | J8: ='GOÄ-ÄD'!F6 -> B. Grundleistungen und allgemeine Leistungen | K8: ='GOÄ-ÄD'!G6 -> I. Allgemeine Beratungen und Untersuchungen | L8: ='GOÄ-ÄD'!A6 -> 8 | M8: ='GOÄ-ÄD'!B6 -> Körperliche Untersuchung | N8: ='GOÄ-ÄD'!C6 -> 20 | P8: ='GOÄ-ÄD'!I6 -> 0
B9: ÄD | I9: GOÄ (GOB) | J9: ='GOÄ-ÄD'!F7 -> B. Grundleistungen und allgemeine Leistungen | K9: ='GOÄ-ÄD'!G7 -> I. Allgemeine Beratungen und Untersuchungen | L9: ='GOÄ-ÄD'!A7 -> 11 | M9: ='GOÄ-ÄD'!B7 -> Digitaluntersuchung Darm | N9: ='GOÄ-ÄD'!C7 -> 4 | P9: ='GOÄ-ÄD'!I7 -> 0
B10: ÄD | I10: GOÄ (GOB) | J10: ='GOÄ-ÄD'!F8 -> B. Grundleistungen und allgemeine Leistungen | K10: ='GOÄ-ÄD'!G8 -> I. Allgemeine Beratungen und Untersuchungen | L10: ='GOÄ-ÄD'!A8 -> 15 | M10: ='GOÄ-ÄD'!B8 -> Einleitung und Koordination flankierender therapeutischer und sozialer Maßnahmen | N10: ='GOÄ-ÄD'!C8 -> 15 | P10: ='GOÄ-ÄD'!I8 -> 0
B11: ÄD | I11: GOÄ (GOB) | J11: ='GOÄ-ÄD'!F9 -> B. Grundleistungen und allgemeine Leistungen | K11: ='GOÄ-ÄD'!G9 -> II. Zuschläge zu Beratungen und Untersuchungen nach Nummer 1, 3, 4, 5, 6, 7 oder 8 | L11: ='GOÄ-ÄD'!A9 -> 27 | M11: ='GOÄ-ÄD'!B9 -> Untersuchung einer Frau zur Früherkennung von Krebserkrankungen | N11: ='GOÄ-ÄD'!C9 -> 26 | P11: ='GOÄ-ÄD'!I9 -> Die Zuschläge nach den Buchstaben A bis D sowie K 1 sind nur mit dem einfachen Gebührensatz berechnungsfähig. Sie dürfen unabhängig von der Anzahl und Kombination der erbrachten Leistungen je Inanspruchnahme des Arztes nur einmal berechnet werden. Neben den Zuschlägen nach den Buchstaben A bis
B12: ÄD | I12: GOÄ (GOB) | J12: ='GOÄ-ÄD'!F10 -> B. Grundleistungen und allgemeine Leistungen | K12: ='GOÄ-ÄD'!G10 -> II. Zuschläge zu Beratungen und Untersuchungen nach Nummer 1, 3, 4, 5, 6, 7 oder 8 | L12: ='GOÄ-ÄD'!A10 -> 28 | M12: ='GOÄ-ÄD'!B10 -> Untersuchung eines Mannes zur Früherkennung von Krebserkrankungen | N12: ='GOÄ-ÄD'!C10 -> 18 | P12: ='GOÄ-ÄD'!I10 -> Die Zuschläge nach den Buchstaben A bis D sowie K 1 sind nur mit dem einfachen Gebührensatz berechnungsfähig. Sie dürfen unabhängig von der Anzahl und Kombination der erbrachten Leistungen je Inanspruchnahme des Arztes nur einmal berechnet werden. Neben den Zuschlägen nach den Buchstaben A bis
B13: ÄD | I13: GOÄ (GOB) | J13: ='GOÄ-ÄD'!F11 -> B. Grundleistungen und allgemeine Leistungen | K13: ='GOÄ-ÄD'!G11 -> II. Zuschläge zu Beratungen und Untersuchungen nach Nummer 1, 3, 4, 5, 6, 7 oder 8 | L13: ='GOÄ-ÄD'!A11 -> 34 | M13: ='GOÄ-ÄD'!B11 -> Erörterung (Dauer min. 20 Minuten) der Auswirkung einer Krankheit | N13: ='GOÄ-ÄD'!C11 -> 20 | P13: ='GOÄ-ÄD'!I11 -> Die Zuschläge nach den Buchstaben A bis D sowie K 1 sind nur mit dem einfachen Gebührensatz berechnungsfähig. Sie dürfen unabhängig von der Anzahl und Kombination der erbrachten Leistungen je Inanspruchnahme des Arztes nur einmal berechnet werden. Neben den Zuschlägen nach den Buchstaben A bis
B14: ÄD | I14: GOÄ (GOB) | J14: ='GOÄ-ÄD'!F12 -> B. Grundleistungen und allgemeine Leistungen | K14: ='GOÄ-ÄD'!G12 -> IV. Visiten, Konsiliartätigkeit, Besuche, Assistenz | L14: ='GOÄ-ÄD'!A12 -> 60 | M14: ='GOÄ-ÄD'!B12 -> Konsiliarische Erörterung zwischen zwei oder mehr Ärzten | N14: ='GOÄ-ÄD'!C12 -> 10 | P14: ='GOÄ-ÄD'!I12 -> 0
B15: ÄD | I15: GOÄ (GOB) | J15: ='GOÄ-ÄD'!F13 -> B. Grundleistungen und allgemeine Leistungen | K15: ='GOÄ-ÄD'!G13 -> VI. Berichte, Briefe | L15: ='GOÄ-ÄD'!A13 -> 70 | M15: ='GOÄ-ÄD'!B13 -> Kurze Bescheinigung | N15: ='GOÄ-ÄD'!C13 -> 1 | P15: ='GOÄ-ÄD'!I13 -> 0
... B630: ÄD | I630: GOÄ (GOB) | J630: ='GOÄ-ÄD'!F628 -> #N/A | K630: ='GOÄ-ÄD'!G628 -> #N/A | L630: ='GOÄ-ÄD'!A628 -> A888 | M630: ='GOÄ-ÄD'!B628 -> Psychiatrische Behandlung zur Reintegration eines Erwachsenen als Gruppenbehandlung | N630: ='GOÄ-ÄD'!C628 -> 12 | P630: ='GOÄ-ÄD'!I628 -> #N/A
B631: nÄD | I631: GOÄ (GOB) nÄD | J631: ='GOÄ-nÄD'!E2 -> Beratung - auch mittels Fernsprecher - | K631: ='GOÄ-nÄD'!G2 -> I. Allgemeine Beratungen und Untersuchungen | L631: ='GOÄ-nÄD'!A2 -> 1 | M631: ='GOÄ-nÄD'!B2 -> Angehörigenberatung | N631: ='GOÄ-nÄD'!C2 -> 30 | P631: ='GOÄ-nÄD'!I2 -> 0
B632: nÄD | I632: GOÄ (GOB) nÄD | J632: ='GOÄ-nÄD'!E3 -> Ausstellung von Wiederholungsrezepten und/oder Überweisungen und/ oder Übermittlung von Befunden oder ärztlichen Anordnungen - auch mittels Fernsprecher - durch die Arzthelferin und/oder Messung von Körperzuständen (z.B. Blutdruck, Temperatur) ohne Beratung, bei einer Inanspruchnahme des Arztes | K632: ='GOÄ-nÄD'!G3 -> I. Allgemeine Beratungen und Untersuchungen | L632: ='GOÄ-nÄD'!A3 -> 2 | M632: ='GOÄ-nÄD'!B3 -> Ausstellung von Wiederholungsrezepten und/oder Überweisungen | N632: ='GOÄ-nÄD'!C3 -> 2 | P632: ='GOÄ-nÄD'!I3 -> 0
B633: nÄD | I633: GOÄ (GOB) nÄD | J633: ='GOÄ-nÄD'!E4 -> Untersuchung zur Erhebung des Ganzkörperstatus, gegebenenfalls einschließlich Dokumentation | K633: ='GOÄ-nÄD'!G4 -> I. Allgemeine Beratungen und Untersuchungen | L633: ='GOÄ-nÄD'!A4 -> 8 | M633: ='GOÄ-nÄD'!B4 -> Körperliche Untersuchung | N633: ='GOÄ-nÄD'!C4 -> 12.5 | P633: ='GOÄ-nÄD'!I4 -> 0
B634: nÄD | I634: GOÄ (GOB) nÄD | J634: ='GOÄ-nÄD'!E5 -> Digitaluntersuchung des Mastdarms und/oder der Prostata | K634: ='GOÄ-nÄD'!G5 -> I. Allgemeine Beratungen und Untersuchungen | L634: ='GOÄ-nÄD'!A5 -> 11 | M634: ='GOÄ-nÄD'!B5 -> Digitaluntersuchung Darm | N634: ='GOÄ-nÄD'!C5 -> 5 | P634: ='GOÄ-nÄD'!I5 -> 0
B635: nÄD | I635: GOÄ (GOB) nÄD | J635: ='GOÄ-nÄD'!E6 -> Strukturierte Schulung einer Einzelperson mit einer Mindestdauer von 20 Minuten (bei Diabetes, Gestationsdiabetes oder Zustand nach Pankreatektomie) - einschließlich Evaluation zur Qualitätssicherung unter diabetologischen Gesichtspunkten zum Erlernen und Umsetzen des Behandlungsmanagements, einschließlich der Auswertung eines standardisierten Fragebogens - | K635: ='GOÄ-nÄD'!G6 -> II. Zuschläge zu Beratungen und Untersuchungen nach Nummer 1, 3, 4, 5, 6, 7 oder 8 | L635: ='GOÄ-nÄD'!A6 -> 33 | M635: ='GOÄ-nÄD'!B6 -> Strukturierte Schulung einer Einzelperson mit einer Mindestdauer von 20 Min. (bei Diabetes, Gestationsdiabetes oder Zustand nach Pankrea- tektomie) - einschl. Evaluation zur Qualitätssicherung | N635: ='GOÄ-nÄD'!C6 -> 20 | P635: ='GOÄ-nÄD'!I6 -> Die Zuschläge nach den Buchstaben A bis D sowie K 1 sind nur mit dem einfachen Gebührensatz berechnungsfähig. Sie dürfen unabhängig von der Anzahl und Kombination der erbrachten Leistungen je Inanspruchnahme des Arztes nur einmal berechnet werden. Neben den Zuschlägen nach den Buchstaben A bis
B636: nÄD | I636: GOÄ (GOB) nÄD | J636: ='GOÄ-nÄD'!E7 -> Ausführlicher schriftlicher Krankheits- und Befundbericht (einschließlich Angaben zur Anamnese, zu dem(n) Befund(en), zur epikritischen Bewertung und gegebenenfalls zur Therapie) | K636: ='GOÄ-nÄD'!G7 -> VI. Berichte, Briefe | L636: ='GOÄ-nÄD'!A7 -> 75 | M636: ='GOÄ-nÄD'!B7 -> Befundbericht | N636: ='GOÄ-nÄD'!C7 -> 0 | P636: ='GOÄ-nÄD'!I7 -> 0
B637: nÄD | I637: GOÄ (GOB) nÄD | J637: ='GOÄ-nÄD'!E8 -> Verband - ausgenommen Schnell- und Sprühverbände, Augen-, Ohrenklappen oder Dreiecktücher - | K637: ='GOÄ-nÄD'!G8 -> I. Anlegen von Verbänden | L637: ='GOÄ-nÄD'!A8 -> 200 | M637: ='GOÄ-nÄD'!B8 -> Verband | N637: ='GOÄ-nÄD'!C8 -> 3 | P637: ='GOÄ-nÄD'!I8 -> Wundverbände nach Nummer 200, die im Zusammenhang mit einer operativen Leistung (auch Ätzung, Fremdkörperentfernung), Punktion, Infusion, Transfusion oder Injektion durchgeführt werden, sind Bestandteil dieser Leistung.
B638: nÄD | I638: GOÄ (GOB) nÄD | J638: ='GOÄ-nÄD'!E9 -> Redressierender Klebeverband des Brustkorbs oder dachziegelförmiger Klebeverband - ausgenommen Nabelverband - | K638: ='GOÄ-nÄD'!G9 -> I. Anlegen von Verbänden | L638: ='GOÄ-nÄD'!A9 -> 201 | M638: ='GOÄ-nÄD'!B9 -> Redressierender Klebeverband Brustkorb | N638: ='GOÄ-nÄD'!C9 -> 6 | P638: ='GOÄ-nÄD'!I9 -> Wundverbände nach Nummer 200, die im Zusammenhang mit einer operativen Leistung (auch Ätzung, Fremdkörperentfernung), Punktion, Infusion, Transfusion oder Injektion durchgeführt werden, sind Bestandteil dieser Leistung.
B639: nÄD | I639: GOÄ (GOB) nÄD | J639: ='GOÄ-nÄD'!E10 -> Zirkulärer Verband des Kopfes oder des Rumpfes (auch als Wundverband); stabilisierender Verband des Halses, des Schulter- oder Hüftgelenks oder einer Extremität über mindestens zwei große Gelenke; Schanz'scher Halskrawattenverband; Kompressionsverband | K639: ='GOÄ-nÄD'!G10 -> I. Anlegen von Verbänden | L639: ='GOÄ-nÄD'!A10 -> 204 | M639: ='GOÄ-nÄD'!B10 -> Zirkulärer Verband, Rucksack oder Desault-Verband | N639: ='GOÄ-nÄD'!C10 -> 9 | P639: ='GOÄ-nÄD'!I10 -> Wundverbände nach Nummer 200, die im Zusammenhang mit einer operativen Leistung (auch Ätzung, Fremdkörperentfernung), Punktion, Infusion, Transfusion oder Injektion durchgeführt werden, sind Bestandteil dieser Leistung.
B640: nÄD | I640: GOÄ (GOB) nÄD | J640: ='GOÄ-nÄD'!E11 -> Tape-Verband eines kleinen Gelenks | K640: ='GOÄ-nÄD'!G11 -> I. Anlegen von Verbänden | L640: ='GOÄ-nÄD'!A11 -> 206 | M640: ='GOÄ-nÄD'!B11 -> Tapeverband eines kleinen Gelenks | N640: ='GOÄ-nÄD'!C11 -> 6 | P640: ='GOÄ-nÄD'!I11 -> Wundverbände nach Nummer 200, die im Zusammenhang mit einer operativen Leistung (auch Ätzung, Fremdkörperentfernung), Punktion, Infusion, Transfusion oder Injektion durchgeführt werden, sind Bestandteil dieser Leistung.
B641: nÄD | I641: GOÄ (GOB) nÄD | J641: ='GOÄ-nÄD'!E12 -> Tape-Verband eines kleinen Gelenks | K641: ='GOÄ-nÄD'!G12 -> I. Anlegen von Verbänden | L641: ='GOÄ-nÄD'!A12 -> 206 | M641: ='GOÄ-nÄD'!B12 -> Tapeverband eines kleinen Gelenks | N641: ='GOÄ-nÄD'!C12 -> 5 | P641: ='GOÄ-nÄD'!I12 -> Wundverbände nach Nummer 200, die im Zusammenhang mit einer operativen Leistung (auch Ätzung, Fremdkörperentfernung), Punktion, Infusion, Transfusion oder Injektion durchgeführt werden, sind Bestandteil dieser Leistung.
B642: nÄD | I642: GOÄ (GOB) nÄD | J642: ='GOÄ-nÄD'!E13 -> Tape-Verband eines großen Gelenks oder Zinkleimverband | K642: ='GOÄ-nÄD'!G13 -> I. Anlegen von Verbänden | L642: ='GOÄ-nÄD'!A13 -> 207 | M642: ='GOÄ-nÄD'!B13 -> Tapeverband eines großen Gelenks | N642: ='GOÄ-nÄD'!C13 -> 9 | P642: ='GOÄ-nÄD'!I13 -> Wundverbände nach Nummer 200, die im Zusammenhang mit einer operativen Leistung (auch Ätzung, Fremdkörperentfernung), Punktion, Infusion, Transfusion oder Injektion durchgeführt werden, sind Bestandteil dieser Leistung.
... B1100: nÄD | I1100: GOÄ (GOB) nÄD | J1100: ='GOÄ-nÄD'!E471 -> #N/A | K1100: ='GOÄ-nÄD'!G471 -> #N/A | L1100: ='GOÄ-nÄD'!A471 -> A618 | M1100: ='GOÄ-nÄD'!B471 -> Lungenfunktionsuntersuchung mit Medikament | N1100: ='GOÄ-nÄD'!C471 -> 40 | P1100: ='GOÄ-nÄD'!I471 -> #N/A
B1101: ÄD | I1101: EBM 2026 | L1101: ='EBM 2026'!A2 -> 1100 | M1101: ='EBM 2026'!B2 -> Unvorhergesehene Inanspruchnahme I | N1101: ='EBM 2026'!C2 -> KA | O1101: ='EBM 2026'!D2 -> ./. | P1101: ='EBM 2026'!E2 -> Keine Eignung
B1102: ÄD | I1102: EBM 2026 | L1102: ='EBM 2026'!A3 -> 1101 | M1102: ='EBM 2026'!B3 -> Unvorhergesehene Inanspruchnahme II | N1102: ='EBM 2026'!C3 -> KA | O1102: ='EBM 2026'!D3 -> ./. | P1102: ='EBM 2026'!E3 -> Keine Eignung
B1103: ÄD | I1103: EBM 2026 | L1103: ='EBM 2026'!A4 -> 1102 | M1103: ='EBM 2026'!B4 -> Inanspruchnahme an Samstagen | N1103: ='EBM 2026'!C4 -> KA | O1103: ='EBM 2026'!D4 -> ./. | P1103: ='EBM 2026'!E4 -> Keine Eignung
B1104: ÄD | I1104: EBM 2026 | L1104: ='EBM 2026'!A5 -> 1205 | M1104: ='EBM 2026'!B5 -> Notfallpauschale (Abklärung, Koordination I) | N1104: ='EBM 2026'!C5 -> 2 | O1104: ='EBM 2026'!D5 -> ./. | P1104: ='EBM 2026'!E5 -> Keine Eignung
B1105: ÄD | I1105: EBM 2026 | L1105: ='EBM 2026'!A6 -> 1207 | M1105: ='EBM 2026'!B6 -> Notfallpauschale (Abklärung, Koordination II) | N1105: ='EBM 2026'!C6 -> 2 | O1105: ='EBM 2026'!D6 -> ./. | P1105: ='EBM 2026'!E6 -> Keine Eignung
B1106: ÄD | I1106: EBM 2026 | L1106: ='EBM 2026'!A7 -> 1210 | M1106: ='EBM 2026'!B7 -> Notfallpauschale I | N1106: ='EBM 2026'!C7 -> KA | O1106: ='EBM 2026'!D7 -> ./. | P1106: ='EBM 2026'!E7 -> Keine Eignung
B1107: ÄD | I1107: EBM 2026 | L1107: ='EBM 2026'!A8 -> 1212 | M1107: ='EBM 2026'!B8 -> Notfallpauschale II | N1107: ='EBM 2026'!C8 -> KA | O1107: ='EBM 2026'!D8 -> ./. | P1107: ='EBM 2026'!E8 -> Keine Eignung
B1108: ÄD | I1108: EBM 2026 | L1108: ='EBM 2026'!A9 -> 1214 | M1108: ='EBM 2026'!B9 -> Notfallkonsultationspauschale I | N1108: ='EBM 2026'!C9 -> KA | O1108: ='EBM 2026'!D9 -> ./. | P1108: ='EBM 2026'!E9 -> Keine Eignung
B1109: ÄD | I1109: EBM 2026 | L1109: ='EBM 2026'!A10 -> 1216 | M1109: ='EBM 2026'!B10 -> Notfallkonsultationspauschale II | N1109: ='EBM 2026'!C10 -> KA | O1109: ='EBM 2026'!D10 -> ./. | P1109: ='EBM 2026'!E10 -> Keine Eignung
B1110: ÄD | I1110: EBM 2026 | L1110: ='EBM 2026'!A11 -> 1218 | M1110: ='EBM 2026'!B11 -> Notfallkonsultationspauschale III | N1110: ='EBM 2026'!C11 -> KA | O1110: ='EBM 2026'!D11 -> ./. | P1110: ='EBM 2026'!E11 -> Keine Eignung
B1111: ÄD | I1111: EBM 2026 | L1111: ='EBM 2026'!A12 -> 1220 | M1111: ='EBM 2026'!B12 -> Reanimationskomplex | N1111: ='EBM 2026'!C12 -> KA | O1111: ='EBM 2026'!D12 -> ./. | P1111: ='EBM 2026'!E12 -> Keine Eignung
B1112: ÄD | I1112: EBM 2026 | L1112: ='EBM 2026'!A13 -> 1221 | M1112: ='EBM 2026'!B13 -> Zuschlag Beatmung | N1112: ='EBM 2026'!C13 -> KA | O1112: ='EBM 2026'!D13 -> ./. | P1112: ='EBM 2026'!E13 -> Keine Eignung
... B3286: ÄD | I3286: EBM 2026 | L3286: ='EBM 2026'!A2187 -> 38207 | M3286: ='EBM 2026'!B2187 -> Zuschlag zur GOP 38105 für den Besuch und die Betreuung eines weiteren Patienten durch einen qualifizierten nichtärztlichen Praxisassistenten (Häuslichkeit) | N3286: ='EBM 2026'!C2187 -> KA | O3286: ='EBM 2026'!D2187 -> ./. | P3286: ='EBM 2026'!E2187 -> Keine Eignung

Sheet GOÄ-ÄD
A1: GOÄ Nummer | B1: Bezeichnung | C1: in Minuten | D1: Bezugsgröße | E1: Leistung | F1: Abschnitt | G1: Unterabschnitt (Kategorie) | H1: ID | I1: Allgemeine Bestimmungen
A2: 2 | B2: Ausstellung von Wiederholungsrezepten und/oder Überweisungen | C2: 2 | D2: / Leistung | E2: =INDEX(tbl_GOAE_Leistungsverzeichnis[Leistung],MATCH(Tabelle1[[#This Row],[GOÄ Nummer]],tbl_GOAE_Leistungsverzeichnis[Mapping ID],0)) -> Ausstellung von Wiederholungsrezepten und/oder Überweisungen und/ oder Übermittlung von Befunden oder ärztlichen Anordnungen - auch mittels Fernsprecher - durch die Arzthelferin und/oder Messung von Körperzuständen (z.B. Blutdruck, Temperatur) ohne Beratung, bei einer Inanspruchnahme des Arztes | F2: =INDEX(tbl_GOAE_Leistungsverzeichnis[Abschnitt],MATCH(Tabelle1[[#This Row],[GOÄ Nummer]],tbl_GOAE_Leistungsverzeichnis[Mapping ID],0)) -> B. Grundleistungen und allgemeine Leistungen | G2: =INDEX(tbl_GOAE_Leistungsverzeichnis[Unterabschnitt (Kategorie)],MATCH(Tabelle1[[#This Row],[GOÄ Nummer]],tbl_GOAE_Leistungsverzeichnis[Mapping ID],0)) -> I. Allgemeine Beratungen und Untersuchungen | H2: =INDEX(tbl_GOAE_Leistungsverzeichnis[Nummer],MATCH(Tabelle1[[#This Row],[GOÄ Nummer]],tbl_GOAE_Leistungsverzeichnis[Mapping ID],0)) -> 2 | I2: =INDEX(tbl_GOAE_Leistungsverzeichnis[Allgemeine Bestimmungen],MATCH(Tabelle1[[#This Row],[GOÄ Nummer]],tbl_GOAE_Leistungsverzeichnis[Mapping ID],0)) -> 0
A3: 3 | B3: Eingehende, das gewöhnliche Maß übersteigende Beratung | C3: 12 | D3: / Leistung | E3: =INDEX(tbl_GOAE_Leistungsverzeichnis[Leistung],MATCH(Tabelle1[[#This Row],[GOÄ Nummer]],tbl_GOAE_Leistungsverzeichnis[Mapping ID],0)) -> Eingehende, das gewöhnliche Maß übersteigende Beratung - auch mittels Fernsprecher - | F3: =INDEX(tbl_GOAE_Leistungsverzeichnis[Abschnitt],MATCH(Tabelle1[[#This Row],[GOÄ Nummer]],tbl_GOAE_Leistungsverzeichnis[Mapping ID],0)) -> B. Grundleistungen und allgemeine Leistungen | G3: =INDEX(tbl_GOAE_Leistungsverzeichnis[Unterabschnitt (Kategorie)],MATCH(Tabelle1[[#This Row],[GOÄ Nummer]],tbl_GOAE_Leistungsverzeichnis[Mapping ID],0)) -> I. Allgemeine Beratungen und Untersuchungen | H3: =INDEX(tbl_GOAE_Leistungsverzeichnis[Nummer],MATCH(Tabelle1[[#This Row],[GOÄ Nummer]],tbl_GOAE_Leistungsverzeichnis[Mapping ID],0)) -> 3 | I3: =INDEX(tbl_GOAE_Leistungsverzeichnis[Allgemeine Bestimmungen],MATCH(Tabelle1[[#This Row],[GOÄ Nummer]],tbl_GOAE_Leistungsverzeichnis[Mapping ID],0)) -> 0
A4: 4 | B4: Erhebung der Fremdanamnese über einen Kranken | C4: 14 | D4: / Leistung | E4: =INDEX(tbl_GOAE_Leistungsverzeichnis[Leistung],MATCH(Tabelle1[[#This Row],[GOÄ Nummer]],tbl_GOAE_Leistungsverzeichnis[Mapping ID],0)) -> Erhebung der Fremdanamnese über einen Kranken und/oder Unterweisung und Führung der Bezugsperson(en) - im Zusammenhang mit der Behandlung eines Kranken - | F4: =INDEX(tbl_GOAE_Leistungsverzeichnis[Abschnitt],MATCH(Tabelle1[[#This Row],[GOÄ Nummer]],tbl_GOAE_Leistungsverzeichnis[Mapping ID],0)) -> B. Grundleistungen und allgemeine Leistungen | G4: =INDEX(tbl_GOAE_Leistungsverzeichnis[Unterabschnitt (Kategorie)],MATCH(Tabelle1[[#This Row],[GOÄ Nummer]],tbl_GOAE_Leistungsverzeichnis[Mapping ID],0)) -> I. Allgemeine Beratungen und Untersuchungen | H4: =INDEX(tbl_GOAE_Leistungsverzeichnis[Nummer],MATCH(Tabelle1[[#This Row],[GOÄ Nummer]],tbl_GOAE_Leistungsverzeichnis[Mapping ID],0)) -> 4 | I4: =INDEX(tbl_GOAE_Leistungsverzeichnis[Allgemeine Bestimmungen],MATCH(Tabelle1[[#This Row],[GOÄ Nummer]],tbl_GOAE_Leistungsverzeichnis[Mapping ID],0)) -> 0
A5: 5 | B5: Ambulante Untersuchung | C5: 15 | D5: / Leistung | E5: =INDEX(tbl_GOAE_Leistungsverzeichnis[Leistung],MATCH(Tabelle1[[#This Row],[GOÄ Nummer]],tbl_GOAE_Leistungsverzeichnis[Mapping ID],0)) -> Symptombezogene Untersuchung | F5: =INDEX(tbl_GOAE_Leistungsverzeichnis[Abschnitt],MATCH(Tabelle1[[#This Row],[GOÄ Nummer]],tbl_GOAE_Leistungsverzeichnis[Mapping ID],0)) -> B. Grundleistungen und allgemeine Leistungen | G5: =INDEX(tbl_GOAE_Leistungsverzeichnis[Unterabschnitt (Kategorie)],MATCH(Tabelle1[[#This Row],[GOÄ Nummer]],tbl_GOAE_Leistungsverzeichnis[Mapping ID],0)) -> I. Allgemeine Beratungen und Untersuchungen | H5: =INDEX(tbl_GOAE_Leistungsverzeichnis[Nummer],MATCH(Tabelle1[[#This Row],[GOÄ Nummer]],tbl_GOAE_Leistungsverzeichnis[Mapping ID],0)) -> 5 | I5: =INDEX(tbl_GOAE_Leistungsverzeichnis[Allgemeine Bestimmungen],MATCH(Tabelle1[[#This Row],[GOÄ Nummer]],tbl_GOAE_Leistungsverzeichnis[Mapping ID],0)) -> 0
A6: 8 | B6: Körperliche Untersuchung | C6: 20 | D6: / Leistung | E6: =INDEX(tbl_GOAE_Leistungsverzeichnis[Leistung],MATCH(Tabelle1[[#This Row],[GOÄ Nummer]],tbl_GOAE_Leistungsverzeichnis[Mapping ID],0)) -> Untersuchung zur Erhebung des Ganzkörperstatus, gegebenenfalls einschließlich Dokumentation | F6: =INDEX(tbl_GOAE_Leistungsverzeichnis[Abschnitt],MATCH(Tabelle1[[#This Row],[GOÄ Nummer]],tbl_GOAE_Leistungsverzeichnis[Mapping ID],0)) -> B. Grundleistungen und allgemeine Leistungen | G6: =INDEX(tbl_GOAE_Leistungsverzeichnis[Unterabschnitt (Kategorie)],MATCH(Tabelle1[[#This Row],[GOÄ Nummer]],tbl_GOAE_Leistungsverzeichnis[Mapping ID],0)) -> I. Allgemeine Beratungen und Untersuchungen | H6: =INDEX(tbl_GOAE_Leistungsverzeichnis[Nummer],MATCH(Tabelle1[[#This Row],[GOÄ Nummer]],tbl_GOAE_Leistungsverzeichnis[Mapping ID],0)) -> 8 | I6: =INDEX(tbl_GOAE_Leistungsverzeichnis[Allgemeine Bestimmungen],MATCH(Tabelle1[[#This Row],[GOÄ Nummer]],tbl_GOAE_Leistungsverzeichnis[Mapping ID],0)) -> 0
A7: 11 | B7: Digitaluntersuchung Darm | C7: 4 | D7: / Leistung | E7: =INDEX(tbl_GOAE_Leistungsverzeichnis[Leistung],MATCH(Tabelle1[[#This Row],[GOÄ Nummer]],tbl_GOAE_Leistungsverzeichnis[Mapping ID],0)) -> Digitaluntersuchung des Mastdarms und/oder der Prostata | F7: =INDEX(tbl_GOAE_Leistungsverzeichnis[Abschnitt],MATCH(Tabelle1[[#This Row],[GOÄ Nummer]],tbl_GOAE_Leistungsverzeichnis[Mapping ID],0)) -> B. Grundleistungen und allgemeine Leistungen | G7: =INDEX(tbl_GOAE_Leistungsverzeichnis[Unterabschnitt (Kategorie)],MATCH(Tabelle1[[#This Row],[GOÄ Nummer]],tbl_GOAE_Leistungsverzeichnis[Mapping ID],0)) -> I. Allgemeine Beratungen und Untersuchungen | H7: =INDEX(tbl_GOAE_Leistungsverzeichnis[Nummer],MATCH(Tabelle1[[#This Row],[GOÄ Nummer]],tbl_GOAE_Leistungsverzeichnis[Mapping ID],0)) -> 11 | I7: =INDEX(tbl_GOAE_Leistungsverzeichnis[Allgemeine Bestimmungen],MATCH(Tabelle1[[#This Row],[GOÄ Nummer]],tbl_GOAE_Leistungsverzeichnis[Mapping ID],0)) -> 0
A8: 15 | B8: Einleitung und Koordination flankierender therapeutischer und sozialer Maßnahmen | C8: 15 | D8: / Leistung | E8: =INDEX(tbl_GOAE_Leistungsverzeichnis[Leistung],MATCH(Tabelle1[[#This Row],[GOÄ Nummer]],tbl_GOAE_Leistungsverzeichnis[Mapping ID],0)) -> Einleitung und Koordination flankierender therapeutischer und sozialer Maßnahmen während der kontinuierlichen ambulanten Betreuung eines chronisch Kranken | F8: =INDEX(tbl_GOAE_Leistungsverzeichnis[Abschnitt],MATCH(Tabelle1[[#This Row],[GOÄ Nummer]],tbl_GOAE_Leistungsverzeichnis[Mapping ID],0)) -> B. Grundleistungen und allgemeine Leistungen | G8: =INDEX(tbl_GOAE_Leistungsverzeichnis[Unterabschnitt (Kategorie)],MATCH(Tabelle1[[#This Row],[GOÄ Nummer]],tbl_GOAE_Leistungsverzeichnis[Mapping ID],0)) -> I. Allgemeine Beratungen und Untersuchungen | H8: =INDEX(tbl_GOAE_Leistungsverzeichnis[Nummer],MATCH(Tabelle1[[#This Row],[GOÄ Nummer]],tbl_GOAE_Leistungsverzeichnis[Mapping ID],0)) -> 15 | I8: =INDEX(tbl_GOAE_Leistungsverzeichnis[Allgemeine Bestimmungen],MATCH(Tabelle1[[#This Row],[GOÄ Nummer]],tbl_GOAE_Leistungsverzeichnis[Mapping ID],0)) -> 0
A9: 27 | B9: Untersuchung einer Frau zur Früherkennung von Krebserkrankungen | C9: 26 | D9: / Leistung | E9: =INDEX(tbl_GOAE_Leistungsverzeichnis[Leistung],MATCH(Tabelle1[[#This Row],[GOÄ Nummer]],tbl_GOAE_Leistungsverzeichnis[Mapping ID],0)) -> Untersuchung einer Frau zur Früherkennung von Krebserkrankungen der Brust, des Genitales, des Rektums und der Haut - einschließlich Erhebung der Anamnese, Abstrichentnahme zur zytologischen Untersuchung, Untersuchung auf Blut im Stuhl und Urinuntersuchung auf Eiweiß, Zucker und Erythrozyten, einschließlich Beratung - | F9: =INDEX(tbl_GOAE_Leistungsverzeichnis[Abschnitt],MATCH(Tabelle1[[#This Row],[GOÄ Nummer]],tbl_GOAE_Leistungsverzeichnis[Mapping ID],0)) -> B. Grundleistungen und allgemeine Leistungen | G9: =INDEX(tbl_GOAE_Leistungsverzeichnis[Unterabschnitt (Kategorie)],MATCH(Tabelle1[[#This Row],[GOÄ Nummer]],tbl_GOAE_Leistungsverzeichnis[Mapping ID],0)) -> II. Zuschläge zu Beratungen und Untersuchungen nach Nummer 1, 3, 4, 5, 6, 7 oder 8 | H9: =INDEX(tbl_GOAE_Leistungsverzeichnis[Nummer],MATCH(Tabelle1[[#This Row],[GOÄ Nummer]],tbl_GOAE_Leistungsverzeichnis[Mapping ID],0)) -> 27 | I9: =INDEX(tbl_GOAE_Leistungsverzeichnis[Allgemeine Bestimmungen],MATCH(Tabelle1[[#This Row],[GOÄ Nummer]],tbl_GOAE_Leistungsverzeichnis[Mapping ID],0)) -> Die Zuschläge nach den Buchstaben A bis D sowie K 1 sind nur mit dem einfachen Gebührensatz berechnungsfähig. Sie dürfen unabhängig von der Anzahl und Kombination der erbrachten Leistungen je Inanspruchnahme des Arztes nur einmal berechnet werden. Neben den Zuschlägen nach den Buchstaben A bis
A10: 28 | B10: Untersuchung eines Mannes zur Früherkennung von Krebserkrankungen | C10: 18 | D10: / Leistung | E10: =INDEX(tbl_GOAE_Leistungsverzeichnis[Leistung],MATCH(Tabelle1[[#This Row],[GOÄ Nummer]],tbl_GOAE_Leistungsverzeichnis[Mapping ID],0)) -> Untersuchung eines Mannes zur Früherkennung von Krebserkrankungen des Rektums, der Prostata, des äußeren Genitales und der Haut - einschließlich Erhebung der Anamnese, Urinuntersuchung auf Eiweiß, Zucker und Erythrozyten sowie Untersuchung auf Blut im Stuhl, einschließlich Beratung - | F10: =INDEX(tbl_GOAE_Leistungsverzeichnis[Abschnitt],MATCH(Tabelle1[[#This Row],[GOÄ Nummer]],tbl_GOAE_Leistungsverzeichnis[Mapping ID],0)) -> B. Grundleistungen und allgemeine Leistungen | G10: =INDEX(tbl_GOAE_Leistungsverzeichnis[Unterabschnitt (Kategorie)],MATCH(Tabelle1[[#This Row],[GOÄ Nummer]],tbl_GOAE_Leistungsverzeichnis[Mapping ID],0)) -> II. Zuschläge zu Beratungen und Untersuchungen nach Nummer 1, 3, 4, 5, 6, 7 oder 8 | H10: =INDEX(tbl_GOAE_Leistungsverzeichnis[Nummer],MATCH(Tabelle1[[#This Row],[GOÄ Nummer]],tbl_GOAE_Leistungsverzeichnis[Mapping ID],0)) -> 28 | I10: =INDEX(tbl_GOAE_Leistungsverzeichnis[Allgemeine Bestimmungen],MATCH(Tabelle1[[#This Row],[GOÄ Nummer]],tbl_GOAE_Leistungsverzeichnis[Mapping ID],0)) -> Die Zuschläge nach den Buchstaben A bis D sowie K 1 sind nur mit dem einfachen Gebührensatz berechnungsfähig. Sie dürfen unabhängig von der Anzahl und Kombination der erbrachten Leistungen je Inanspruchnahme des Arztes nur einmal berechnet werden. Neben den Zuschlägen nach den Buchstaben A bis
A11: 34 | B11: Erörterung (Dauer min. 20 Minuten) der Auswirkung einer Krankheit | C11: 20 | D11: / Leistung | E11: =INDEX(tbl_GOAE_Leistungsverzeichnis[Leistung],MATCH(Tabelle1[[#This Row],[GOÄ Nummer]],tbl_GOAE_Leistungsverzeichnis[Mapping ID],0)) -> Erörterung (Dauer mindestens 20 Minuten) der Auswirkungen einer Krankheit auf die Lebensgestaltung in unmittelbarem Zusammenhang mit der Feststellung oder erheblichen Verschlimmerung einer nachhaltig lebensverändernden oder lebensbedrohenden Erkrankung - gegebenenfalls einschließlich Planung eines operativen Eingriffs und Abwägung seiner Konsequenzen und Risiken -, einschließlich Beratung - gegebenenfalls unter Einbeziehung von Bezugspersonen - | F11: =INDEX(tbl_GOAE_Leistungsverzeichnis[Abschnitt],MATCH(Tabelle1[[#This Row],[GOÄ Nummer]],tbl_GOAE_Leistungsverzeichnis[Mapping ID],0)) -> B. Grundleistungen und allgemeine Leistungen | G11: =INDEX(tbl_GOAE_Leistungsverzeichnis[Unterabschnitt (Kategorie)],MATCH(Tabelle1[[#This Row],[GOÄ Nummer]],tbl_GOAE_Leistungsverzeichnis[Mapping ID],0)) -> II. Zuschläge zu Beratungen und Untersuchungen nach Nummer 1, 3, 4, 5, 6, 7 oder 8 | H11: =INDEX(tbl_GOAE_Leistungsverzeichnis[Nummer],MATCH(Tabelle1[[#This Row],[GOÄ Nummer]],tbl_GOAE_Leistungsverzeichnis[Mapping ID],0)) -> 34 | I11: =INDEX(tbl_GOAE_Leistungsverzeichnis[Allgemeine Bestimmungen],MATCH(Tabelle1[[#This Row],[GOÄ Nummer]],tbl_GOAE_Leistungsverzeichnis[Mapping ID],0)) -> Die Zuschläge nach den Buchstaben A bis D sowie K 1 sind nur mit dem einfachen Gebührensatz berechnungsfähig. Sie dürfen unabhängig von der Anzahl und Kombination der erbrachten Leistungen je Inanspruchnahme des Arztes nur einmal berechnet werden. Neben den Zuschlägen nach den Buchstaben A bis
A12: 60 | B12: Konsiliarische Erörterung zwischen zwei oder mehr Ärzten | C12: 10 | D12: / Leistung | E12: =INDEX(tbl_GOAE_Leistungsverzeichnis[Leistung],MATCH(Tabelle1[[#This Row],[GOÄ Nummer]],tbl_GOAE_Leistungsverzeichnis[Mapping ID],0)) -> Konsiliarische Erörterung zwischen zwei oder mehr liquidationsberechtigten Ärzten, für jeden Arzt | F12: =INDEX(tbl_GOAE_Leistungsverzeichnis[Abschnitt],MATCH(Tabelle1[[#This Row],[GOÄ Nummer]],tbl_GOAE_Leistungsverzeichnis[Mapping ID],0)) -> B. Grundleistungen und allgemeine Leistungen | G12: =INDEX(tbl_GOAE_Leistungsverzeichnis[Unterabschnitt (Kategorie)],MATCH(Tabelle1[[#This Row],[GOÄ Nummer]],tbl_GOAE_Leistungsverzeichnis[Mapping ID],0)) -> IV. Visiten, Konsiliartätigkeit, Besuche, Assistenz | H12: =INDEX(tbl_GOAE_Leistungsverzeichnis[Nummer],MATCH(Tabelle1[[#This Row],[GOÄ Nummer]],tbl_GOAE_Leistungsverzeichnis[Mapping ID],0)) -> 60 | I12: =INDEX(tbl_GOAE_Leistungsverzeichnis[Allgemeine Bestimmungen],MATCH(Tabelle1[[#This Row],[GOÄ Nummer]],tbl_GOAE_Leistungsverzeichnis[Mapping ID],0)) -> 0
A13: 70 | B13: Kurze Bescheinigung | C13: 1 | D13: / Leistung | E13: =INDEX(tbl_GOAE_Leistungsverzeichnis[Leistung],MATCH(Tabelle1[[#This Row],[GOÄ Nummer]],tbl_GOAE_Leistungsverzeichnis[Mapping ID],0)) -> Kurze Bescheinigung oder kurzes Zeugnis, Arbeitsunfähigkeitsbescheinigung | F13: =INDEX(tbl_GOAE_Leistungsverzeichnis[Abschnitt],MATCH(Tabelle1[[#This Row],[GOÄ Nummer]],tbl_GOAE_Leistungsverzeichnis[Mapping ID],0)) -> B. Grundleistungen und allgemeine Leistungen | G13: =INDEX(tbl_GOAE_Leistungsverzeichnis[Unterabschnitt (Kategorie)],MATCH(Tabelle1[[#This Row],[GOÄ Nummer]],tbl_GOAE_Leistungsverzeichnis[Mapping ID],0)) -> VI. Berichte, Briefe | H13: =INDEX(tbl_GOAE_Leistungsverzeichnis[Nummer],MATCH(Tabelle1[[#This Row],[GOÄ Nummer]],tbl_GOAE_Leistungsverzeichnis[Mapping ID],0)) -> 70 | I13: =INDEX(tbl_GOAE_Leistungsverzeichnis[Allgemeine Bestimmungen],MATCH(Tabelle1[[#This Row],[GOÄ Nummer]],tbl_GOAE_Leistungsverzeichnis[Mapping ID],0)) -> 0
... A622: 6100 | B622: Kernspintomographie | C622: 60 | D622: / Leistung | E622: =INDEX(tbl_GOAE_Leistungsverzeichnis[Leistung],MATCH(Tabelle1[[#This Row],[GOÄ Nummer]],tbl_GOAE_Leistungsverzeichnis[Mapping ID],0)) -> #N/A | F622: =INDEX(tbl_GOAE_Leistungsverzeichnis[Abschnitt],MATCH(Tabelle1[[#This Row],[GOÄ Nummer]],tbl_GOAE_Leistungsverzeichnis[Mapping ID],0)) -> #N/A | G622: =INDEX(tbl_GOAE_Leistungsverzeichnis[Unterabschnitt (Kategorie)],MATCH(Tabelle1[[#This Row],[GOÄ Nummer]],tbl_GOAE_Leistungsverzeichnis[Mapping ID],0)) -> #N/A | H622: =INDEX(tbl_GOAE_Leistungsverzeichnis[Nummer],MATCH(Tabelle1[[#This Row],[GOÄ Nummer]],tbl_GOAE_Leistungsverzeichnis[Mapping ID],0)) -> #N/A | I622: =INDEX(tbl_GOAE_Leistungsverzeichnis[Allgemeine Bestimmungen],MATCH(Tabelle1[[#This Row],[GOÄ Nummer]],tbl_GOAE_Leistungsverzeichnis[Mapping ID],0)) -> #N/A
A623: 286a | B623: Rehinfusion jeder weiteren Einheit (mindestens 200ml) Eigenblut oder Eigenplasma im Anschluss an die Leistung nach der Nummer 286 einschl. Identitätssicherung im AB0 System (Bedsidetest) | C623: 8 | D623: / Leistung | E623: =INDEX(tbl_GOAE_Leistungsverzeichnis[Leistung],MATCH(Tabelle1[[#This Row],[GOÄ Nummer]],tbl_GOAE_Leistungsverzeichnis[Mapping ID],0)) -> #N/A | F623: =INDEX(tbl_GOAE_Leistungsverzeichnis[Abschnitt],MATCH(Tabelle1[[#This Row],[GOÄ Nummer]],tbl_GOAE_Leistungsverzeichnis[Mapping ID],0)) -> #N/A | G623: =INDEX(tbl_GOAE_Leistungsverzeichnis[Unterabschnitt (Kategorie)],MATCH(Tabelle1[[#This Row],[GOÄ Nummer]],tbl_GOAE_Leistungsverzeichnis[Mapping ID],0)) -> #N/A | H623: =INDEX(tbl_GOAE_Leistungsverzeichnis[Nummer],MATCH(Tabelle1[[#This Row],[GOÄ Nummer]],tbl_GOAE_Leistungsverzeichnis[Mapping ID],0)) -> #N/A | I623: =INDEX(tbl_GOAE_Leistungsverzeichnis[Allgemeine Bestimmungen],MATCH(Tabelle1[[#This Row],[GOÄ Nummer]],tbl_GOAE_Leistungsverzeichnis[Mapping ID],0)) -> #N/A
A624: 605a | B624: Darstellung der Flussvolumenkurve bei spirographischen Untersuchungen | C624: 6 | D624: / Leistung | E624: =INDEX(tbl_GOAE_Leistungsverzeichnis[Leistung],MATCH(Tabelle1[[#This Row],[GOÄ Nummer]],tbl_GOAE_Leistungsverzeichnis[Mapping ID],0)) -> #N/A | F624: =INDEX(tbl_GOAE_Leistungsverzeichnis[Abschnitt],MATCH(Tabelle1[[#This Row],[GOÄ Nummer]],tbl_GOAE_Leistungsverzeichnis[Mapping ID],0)) -> #N/A | G624: =INDEX(tbl_GOAE_Leistungsverzeichnis[Unterabschnitt (Kategorie)],MATCH(Tabelle1[[#This Row],[GOÄ Nummer]],tbl_GOAE_Leistungsverzeichnis[Mapping ID],0)) -> #N/A | H624: =INDEX(tbl_GOAE_Leistungsverzeichnis[Nummer],MATCH(Tabelle1[[#This Row],[GOÄ Nummer]],tbl_GOAE_Leistungsverzeichnis[Mapping ID],0)) -> #N/A | I624: =INDEX(tbl_GOAE_Leistungsverzeichnis[Allgemeine Bestimmungen],MATCH(Tabelle1[[#This Row],[GOÄ Nummer]],tbl_GOAE_Leistungsverzeichnis[Mapping ID],0)) -> #N/A
A625: 827a | B625: Schlafentzugs-EEG | C625: 20 | D625: / Leistung | E625: =INDEX(tbl_GOAE_Leistungsverzeichnis[Leistung],MATCH(Tabelle1[[#This Row],[GOÄ Nummer]],tbl_GOAE_Leistungsverzeichnis[Mapping ID],0)) -> #N/A | F625: =INDEX(tbl_GOAE_Leistungsverzeichnis[Abschnitt],MATCH(Tabelle1[[#This Row],[GOÄ Nummer]],tbl_GOAE_Leistungsverzeichnis[Mapping ID],0)) -> #N/A | G625: =INDEX(tbl_GOAE_Leistungsverzeichnis[Unterabschnitt (Kategorie)],MATCH(Tabelle1[[#This Row],[GOÄ Nummer]],tbl_GOAE_Leistungsverzeichnis[Mapping ID],0)) -> #N/A | H625: =INDEX(tbl_GOAE_Leistungsverzeichnis[Nummer],MATCH(Tabelle1[[#This Row],[GOÄ Nummer]],tbl_GOAE_Leistungsverzeichnis[Mapping ID],0)) -> #N/A | I625: =INDEX(tbl_GOAE_Leistungsverzeichnis[Allgemeine Bestimmungen],MATCH(Tabelle1[[#This Row],[GOÄ Nummer]],tbl_GOAE_Leistungsverzeichnis[Mapping ID],0)) -> #N/A
A626: A353 | B626: Einbringung des Kontrastmittels mittels intraarterieller Hochdruckinjektion zur selektive Arteriographie (z.B. Nierenarterie), einschließlich Röntgenkontrolle und ggf. fortlaufender EKG Kontrolle, je | C626: 38 | D626: / Leistung | E626: =INDEX(tbl_GOAE_Leistungsverzeichnis[Leistung],MATCH(Tabelle1[[#This Row],[GOÄ Nummer]],tbl_GOAE_Leistungsverzeichnis[Mapping ID],0)) -> #N/A | F626: =INDEX(tbl_GOAE_Leistungsverzeichnis[Abschnitt],MATCH(Tabelle1[[#This Row],[GOÄ Nummer]],tbl_GOAE_Leistungsverzeichnis[Mapping ID],0)) -> #N/A | G626: =INDEX(tbl_GOAE_Leistungsverzeichnis[Unterabschnitt (Kategorie)],MATCH(Tabelle1[[#This Row],[GOÄ Nummer]],tbl_GOAE_Leistungsverzeichnis[Mapping ID],0)) -> #N/A | H626: =INDEX(tbl_GOAE_Leistungsverzeichnis[Nummer],MATCH(Tabelle1[[#This Row],[GOÄ Nummer]],tbl_GOAE_Leistungsverzeichnis[Mapping ID],0)) -> #N/A | I626: =INDEX(tbl_GOAE_Leistungsverzeichnis[Allgemeine Bestimmungen],MATCH(Tabelle1[[#This Row],[GOÄ Nummer]],tbl_GOAE_Leistungsverzeichnis[Mapping ID],0)) -> #N/A
A627: A795 | B627: Kipptisch-Untersuchung | C627: 20 | D627: / Leistung | E627: =INDEX(tbl_GOAE_Leistungsverzeichnis[Leistung],MATCH(Tabelle1[[#This Row],[GOÄ Nummer]],tbl_GOAE_Leistungsverzeichnis[Mapping ID],0)) -> #N/A | F627: =INDEX(tbl_GOAE_Leistungsverzeichnis[Abschnitt],MATCH(Tabelle1[[#This Row],[GOÄ Nummer]],tbl_GOAE_Leistungsverzeichnis[Mapping ID],0)) -> #N/A | G627: =INDEX(tbl_GOAE_Leistungsverzeichnis[Unterabschnitt (Kategorie)],MATCH(Tabelle1[[#This Row],[GOÄ Nummer]],tbl_GOAE_Leistungsverzeichnis[Mapping ID],0)) -> #N/A | H627: =INDEX(tbl_GOAE_Leistungsverzeichnis[Nummer],MATCH(Tabelle1[[#This Row],[GOÄ Nummer]],tbl_GOAE_Leistungsverzeichnis[Mapping ID],0)) -> #N/A | I627: =INDEX(tbl_GOAE_Leistungsverzeichnis[Allgemeine Bestimmungen],MATCH(Tabelle1[[#This Row],[GOÄ Nummer]],tbl_GOAE_Leistungsverzeichnis[Mapping ID],0)) -> #N/A
A628: A888 | B628: Psychiatrische Behandlung zur Reintegration eines Erwachsenen als Gruppenbehandlung | C628: 12 | D628: / Leistung | E628: =INDEX(tbl_GOAE_Leistungsverzeichnis[Leistung],MATCH(Tabelle1[[#This Row],[GOÄ Nummer]],tbl_GOAE_Leistungsverzeichnis[Mapping ID],0)) -> #N/A | F628: =INDEX(tbl_GOAE_Leistungsverzeichnis[Abschnitt],MATCH(Tabelle1[[#This Row],[GOÄ Nummer]],tbl_GOAE_Leistungsverzeichnis[Mapping ID],0)) -> #N/A | G628: =INDEX(tbl_GOAE_Leistungsverzeichnis[Unterabschnitt (Kategorie)],MATCH(Tabelle1[[#This Row],[GOÄ Nummer]],tbl_GOAE_Leistungsverzeichnis[Mapping ID],0)) -> #N/A | H628: =INDEX(tbl_GOAE_Leistungsverzeichnis[Nummer],MATCH(Tabelle1[[#This Row],[GOÄ Nummer]],tbl_GOAE_Leistungsverzeichnis[Mapping ID],0)) -> #N/A | I628: =INDEX(tbl_GOAE_Leistungsverzeichnis[Allgemeine Bestimmungen],MATCH(Tabelle1[[#This Row],[GOÄ Nummer]],tbl_GOAE_Leistungsverzeichnis[Mapping ID],0)) -> #N/A

Sheet GOÄ-nÄD
A1: GOÄ Nummer | B1: Bezeichnung | C1: in Minuten | D1: Bezugsgröße | E1: Leistung | F1: Abschnitt | G1: Unterabschnitt (Kategorie) | H1: ID | I1: Allgemeine Bestimmungen
A2: 1 | B2: Angehörigenberatung | C2: 30 | D2: Min. / Beratung | E2: =INDEX(tbl_GOAE_Leistungsverzeichnis[Leistung],MATCH(Tabelle5[[#This Row],[GOÄ Nummer]],tbl_GOAE_Leistungsverzeichnis[Mapping ID],0)) -> Beratung - auch mittels Fernsprecher - | F2: =INDEX(tbl_GOAE_Leistungsverzeichnis[Abschnitt],MATCH(Tabelle5[[#This Row],[GOÄ Nummer]],tbl_GOAE_Leistungsverzeichnis[Mapping ID],0)) -> B. Grundleistungen und allgemeine Leistungen | G2: =INDEX(tbl_GOAE_Leistungsverzeichnis[Unterabschnitt (Kategorie)],MATCH(Tabelle5[[#This Row],[GOÄ Nummer]],tbl_GOAE_Leistungsverzeichnis[Mapping ID],0)) -> I. Allgemeine Beratungen und Untersuchungen | H2: =INDEX(tbl_GOAE_Leistungsverzeichnis[Nummer],MATCH(Tabelle5[[#This Row],[GOÄ Nummer]],tbl_GOAE_Leistungsverzeichnis[Mapping ID],0)) -> 1 | I2: =INDEX(tbl_GOAE_Leistungsverzeichnis[Allgemeine Bestimmungen],MATCH(Tabelle5[[#This Row],[GOÄ Nummer]],tbl_GOAE_Leistungsverzeichnis[Mapping ID],0)) -> 0
A3: 2 | B3: Ausstellung von Wiederholungsrezepten und/oder Überweisungen | C3: 2 | D3: Min. / Patient | E3: =INDEX(tbl_GOAE_Leistungsverzeichnis[Leistung],MATCH(Tabelle5[[#This Row],[GOÄ Nummer]],tbl_GOAE_Leistungsverzeichnis[Mapping ID],0)) -> Ausstellung von Wiederholungsrezepten und/oder Überweisungen und/ oder Übermittlung von Befunden oder ärztlichen Anordnungen - auch mittels Fernsprecher - durch die Arzthelferin und/oder Messung von Körperzuständen (z.B. Blutdruck, Temperatur) ohne Beratung, bei einer Inanspruchnahme des Arztes | F3: =INDEX(tbl_GOAE_Leistungsverzeichnis[Abschnitt],MATCH(Tabelle5[[#This Row],[GOÄ Nummer]],tbl_GOAE_Leistungsverzeichnis[Mapping ID],0)) -> B. Grundleistungen und allgemeine Leistungen | G3: =INDEX(tbl_GOAE_Leistungsverzeichnis[Unterabschnitt (Kategorie)],MATCH(Tabelle5[[#This Row],[GOÄ Nummer]],tbl_GOAE_Leistungsverzeichnis[Mapping ID],0)) -> I. Allgemeine Beratungen und Untersuchungen | H3: =INDEX(tbl_GOAE_Leistungsverzeichnis[Nummer],MATCH(Tabelle5[[#This Row],[GOÄ Nummer]],tbl_GOAE_Leistungsverzeichnis[Mapping ID],0)) -> 2 | I3: =INDEX(tbl_GOAE_Leistungsverzeichnis[Allgemeine Bestimmungen],MATCH(Tabelle5[[#This Row],[GOÄ Nummer]],tbl_GOAE_Leistungsverzeichnis[Mapping ID],0)) -> 0
A4: 8 | B4: Körperliche Untersuchung | C4: 12.5 | D4: Min. / Patient | E4: =INDEX(tbl_GOAE_Leistungsverzeichnis[Leistung],MATCH(Tabelle5[[#This Row],[GOÄ Nummer]],tbl_GOAE_Leistungsverzeichnis[Mapping ID],0)) -> Untersuchung zur Erhebung des Ganzkörperstatus, gegebenenfalls einschließlich Dokumentation | F4: =INDEX(tbl_GOAE_Leistungsverzeichnis[Abschnitt],MATCH(Tabelle5[[#This Row],[GOÄ Nummer]],tbl_GOAE_Leistungsverzeichnis[Mapping ID],0)) -> B. Grundleistungen und allgemeine Leistungen | G4: =INDEX(tbl_GOAE_Leistungsverzeichnis[Unterabschnitt (Kategorie)],MATCH(Tabelle5[[#This Row],[GOÄ Nummer]],tbl_GOAE_Leistungsverzeichnis[Mapping ID],0)) -> I. Allgemeine Beratungen und Untersuchungen | H4: =INDEX(tbl_GOAE_Leistungsverzeichnis[Nummer],MATCH(Tabelle5[[#This Row],[GOÄ Nummer]],tbl_GOAE_Leistungsverzeichnis[Mapping ID],0)) -> 8 | I4: =INDEX(tbl_GOAE_Leistungsverzeichnis[Allgemeine Bestimmungen],MATCH(Tabelle5[[#This Row],[GOÄ Nummer]],tbl_GOAE_Leistungsverzeichnis[Mapping ID],0)) -> 0
A5: 11 | B5: Digitaluntersuchung Darm | C5: 5 | D5: Min. / Patient | E5: =INDEX(tbl_GOAE_Leistungsverzeichnis[Leistung],MATCH(Tabelle5[[#This Row],[GOÄ Nummer]],tbl_GOAE_Leistungsverzeichnis[Mapping ID],0)) -> Digitaluntersuchung des Mastdarms und/oder der Prostata | F5: =INDEX(tbl_GOAE_Leistungsverzeichnis[Abschnitt],MATCH(Tabelle5[[#This Row],[GOÄ Nummer]],tbl_GOAE_Leistungsverzeichnis[Mapping ID],0)) -> B. Grundleistungen und allgemeine Leistungen | G5: =INDEX(tbl_GOAE_Leistungsverzeichnis[Unterabschnitt (Kategorie)],MATCH(Tabelle5[[#This Row],[GOÄ Nummer]],tbl_GOAE_Leistungsverzeichnis[Mapping ID],0)) -> I. Allgemeine Beratungen und Untersuchungen | H5: =INDEX(tbl_GOAE_Leistungsverzeichnis[Nummer],MATCH(Tabelle5[[#This Row],[GOÄ Nummer]],tbl_GOAE_Leistungsverzeichnis[Mapping ID],0)) -> 11 | I5: =INDEX(tbl_GOAE_Leistungsverzeichnis[Allgemeine Bestimmungen],MATCH(Tabelle5[[#This Row],[GOÄ Nummer]],tbl_GOAE_Leistungsverzeichnis[Mapping ID],0)) -> 0
A6: 33 | B6: Strukturierte Schulung einer Einzelperson mit einer Mindestdauer von 20 Min. (bei Diabetes, Gestationsdiabetes oder Zustand nach Pankrea- tektomie) - einschl. Evaluation zur Qualitätssicherung | C6: 20 | D6: Min. / Patient | E6: =INDEX(tbl_GOAE_Leistungsverzeichnis[Leistung],MATCH(Tabelle5[[#This Row],[GOÄ Nummer]],tbl_GOAE_Leistungsverzeichnis[Mapping ID],0)) -> Strukturierte Schulung einer Einzelperson mit einer Mindestdauer von 20 Minuten (bei Diabetes, Gestationsdiabetes oder Zustand nach Pankreatektomie) - einschließlich Evaluation zur Qualitätssicherung unter diabetologischen Gesichtspunkten zum Erlernen und Umsetzen des Behandlungsmanagements, einschließlich der Auswertung eines standardisierten Fragebogens - | F6: =INDEX(tbl_GOAE_Leistungsverzeichnis[Abschnitt],MATCH(Tabelle5[[#This Row],[GOÄ Nummer]],tbl_GOAE_Leistungsverzeichnis[Mapping ID],0)) -> B. Grundleistungen und allgemeine Leistungen | G6: =INDEX(tbl_GOAE_Leistungsverzeichnis[Unterabschnitt (Kategorie)],MATCH(Tabelle5[[#This Row],[GOÄ Nummer]],tbl_GOAE_Leistungsverzeichnis[Mapping ID],0)) -> II. Zuschläge zu Beratungen und Untersuchungen nach Nummer 1, 3, 4, 5, 6, 7 oder 8 | H6: =INDEX(tbl_GOAE_Leistungsverzeichnis[Nummer],MATCH(Tabelle5[[#This Row],[GOÄ Nummer]],tbl_GOAE_Leistungsverzeichnis[Mapping ID],0)) -> 33 | I6: =INDEX(tbl_GOAE_Leistungsverzeichnis[Allgemeine Bestimmungen],MATCH(Tabelle5[[#This Row],[GOÄ Nummer]],tbl_GOAE_Leistungsverzeichnis[Mapping ID],0)) -> Die Zuschläge nach den Buchstaben A bis D sowie K 1 sind nur mit dem einfachen Gebührensatz berechnungsfähig. Sie dürfen unabhängig von der Anzahl und Kombination der erbrachten Leistungen je Inanspruchnahme des Arztes nur einmal berechnet werden. Neben den Zuschlägen nach den Buchstaben A bis
A7: 75 | B7: Befundbericht | C7: 0 | D7: Min. / Patient | E7: =INDEX(tbl_GOAE_Leistungsverzeichnis[Leistung],MATCH(Tabelle5[[#This Row],[GOÄ Nummer]],tbl_GOAE_Leistungsverzeichnis[Mapping ID],0)) -> Ausführlicher schriftlicher Krankheits- und Befundbericht (einschließlich Angaben zur Anamnese, zu dem(n) Befund(en), zur epikritischen Bewertung und gegebenenfalls zur Therapie) | F7: =INDEX(tbl_GOAE_Leistungsverzeichnis[Abschnitt],MATCH(Tabelle5[[#This Row],[GOÄ Nummer]],tbl_GOAE_Leistungsverzeichnis[Mapping ID],0)) -> B. Grundleistungen und allgemeine Leistungen | G7: =INDEX(tbl_GOAE_Leistungsverzeichnis[Unterabschnitt (Kategorie)],MATCH(Tabelle5[[#This Row],[GOÄ Nummer]],tbl_GOAE_Leistungsverzeichnis[Mapping ID],0)) -> VI. Berichte, Briefe | H7: =INDEX(tbl_GOAE_Leistungsverzeichnis[Nummer],MATCH(Tabelle5[[#This Row],[GOÄ Nummer]],tbl_GOAE_Leistungsverzeichnis[Mapping ID],0)) -> 75 | I7: =INDEX(tbl_GOAE_Leistungsverzeichnis[Allgemeine Bestimmungen],MATCH(Tabelle5[[#This Row],[GOÄ Nummer]],tbl_GOAE_Leistungsverzeichnis[Mapping ID],0)) -> 0
A8: 200 | B8: Verband | C8: 3 | D8: Min. / Patient | E8: =INDEX(tbl_GOAE_Leistungsverzeichnis[Leistung],MATCH(Tabelle5[[#This Row],[GOÄ Nummer]],tbl_GOAE_Leistungsverzeichnis[Mapping ID],0)) -> Verband - ausgenommen Schnell- und Sprühverbände, Augen-, Ohrenklappen oder Dreiecktücher - | F8: =INDEX(tbl_GOAE_Leistungsverzeichnis[Abschnitt],MATCH(Tabelle5[[#This Row],[GOÄ Nummer]],tbl_GOAE_Leistungsverzeichnis[Mapping ID],0)) -> C. Nichtgebietsbezogene Sonderleistungen | G8: =INDEX(tbl_GOAE_Leistungsverzeichnis[Unterabschnitt (Kategorie)],MATCH(Tabelle5[[#This Row],[GOÄ Nummer]],tbl_GOAE_Leistungsverzeichnis[Mapping ID],0)) -> I. Anlegen von Verbänden | H8: =INDEX(tbl_GOAE_Leistungsverzeichnis[Nummer],MATCH(Tabelle5[[#This Row],[GOÄ Nummer]],tbl_GOAE_Leistungsverzeichnis[Mapping ID],0)) -> 200 | I8: =INDEX(tbl_GOAE_Leistungsverzeichnis[Allgemeine Bestimmungen],MATCH(Tabelle5[[#This Row],[GOÄ Nummer]],tbl_GOAE_Leistungsverzeichnis[Mapping ID],0)) -> Wundverbände nach Nummer 200, die im Zusammenhang mit einer operativen Leistung (auch Ätzung, Fremdkörperentfernung), Punktion, Infusion, Transfusion oder Injektion durchgeführt werden, sind Bestandteil dieser Leistung.
A9: 201 | B9: Redressierender Klebeverband Brustkorb | C9: 6 | D9: Min. / Patient | E9: =INDEX(tbl_GOAE_Leistungsverzeichnis[Leistung],MATCH(Tabelle5[[#This Row],[GOÄ Nummer]],tbl_GOAE_Leistungsverzeichnis[Mapping ID],0)) -> Redressierender Klebeverband des Brustkorbs oder dachziegelförmiger Klebeverband - ausgenommen Nabelverband - | F9: =INDEX(tbl_GOAE_Leistungsverzeichnis[Abschnitt],MATCH(Tabelle5[[#This Row],[GOÄ Nummer]],tbl_GOAE_Leistungsverzeichnis[Mapping ID],0)) -> C. Nichtgebietsbezogene Sonderleistungen | G9: =INDEX(tbl_GOAE_Leistungsverzeichnis[Unterabschnitt (Kategorie)],MATCH(Tabelle5[[#This Row],[GOÄ Nummer]],tbl_GOAE_Leistungsverzeichnis[Mapping ID],0)) -> I. Anlegen von Verbänden | H9: =INDEX(tbl_GOAE_Leistungsverzeichnis[Nummer],MATCH(Tabelle5[[#This Row],[GOÄ Nummer]],tbl_GOAE_Leistungsverzeichnis[Mapping ID],0)) -> 201 | I9: =INDEX(tbl_GOAE_Leistungsverzeichnis[Allgemeine Bestimmungen],MATCH(Tabelle5[[#This Row],[GOÄ Nummer]],tbl_GOAE_Leistungsverzeichnis[Mapping ID],0)) -> Wundverbände nach Nummer 200, die im Zusammenhang mit einer operativen Leistung (auch Ätzung, Fremdkörperentfernung), Punktion, Infusion, Transfusion oder Injektion durchgeführt werden, sind Bestandteil dieser Leistung.
A10: 204 | B10: Zirkulärer Verband, Rucksack oder Desault-Verband | C10: 9 | D10: Min. / Patient | E10: =INDEX(tbl_GOAE_Leistungsverzeichnis[Leistung],MATCH(Tabelle5[[#This Row],[GOÄ Nummer]],tbl_GOAE_Leistungsverzeichnis[Mapping ID],0)) -> Zirkulärer Verband des Kopfes oder des Rumpfes (auch als Wundverband); stabilisierender Verband des Halses, des Schulter- oder Hüftgelenks oder einer Extremität über mindestens zwei große Gelenke; Schanz'scher Halskrawattenverband; Kompressionsverband | F10: =INDEX(tbl_GOAE_Leistungsverzeichnis[Abschnitt],MATCH(Tabelle5[[#This Row],[GOÄ Nummer]],tbl_GOAE_Leistungsverzeichnis[Mapping ID],0)) -> C. Nichtgebietsbezogene Sonderleistungen | G10: =INDEX(tbl_GOAE_Leistungsverzeichnis[Unterabschnitt (Kategorie)],MATCH(Tabelle5[[#This Row],[GOÄ Nummer]],tbl_GOAE_Leistungsverzeichnis[Mapping ID],0)) -> I. Anlegen von Verbänden | H10: =INDEX(tbl_GOAE_Leistungsverzeichnis[Nummer],MATCH(Tabelle5[[#This Row],[GOÄ Nummer]],tbl_GOAE_Leistungsverzeichnis[Mapping ID],0)) -> 204 | I10: =INDEX(tbl_GOAE_Leistungsverzeichnis[Allgemeine Bestimmungen],MATCH(Tabelle5[[#This Row],[GOÄ Nummer]],tbl_GOAE_Leistungsverzeichnis[Mapping ID],0)) -> Wundverbände nach Nummer 200, die im Zusammenhang mit einer operativen Leistung (auch Ätzung, Fremdkörperentfernung), Punktion, Infusion, Transfusion oder Injektion durchgeführt werden, sind Bestandteil dieser Leistung.
A11: 206 | B11: Tapeverband eines kleinen Gelenks | C11: 6 | D11: Min. / Patient | E11: =INDEX(tbl_GOAE_Leistungsverzeichnis[Leistung],MATCH(Tabelle5[[#This Row],[GOÄ Nummer]],tbl_GOAE_Leistungsverzeichnis[Mapping ID],0)) -> Tape-Verband eines kleinen Gelenks | F11: =INDEX(tbl_GOAE_Leistungsverzeichnis[Abschnitt],MATCH(Tabelle5[[#This Row],[GOÄ Nummer]],tbl_GOAE_Leistungsverzeichnis[Mapping ID],0)) -> C. Nichtgebietsbezogene Sonderleistungen | G11: =INDEX(tbl_GOAE_Leistungsverzeichnis[Unterabschnitt (Kategorie)],MATCH(Tabelle5[[#This Row],[GOÄ Nummer]],tbl_GOAE_Leistungsverzeichnis[Mapping ID],0)) -> I. Anlegen von Verbänden | H11: =INDEX(tbl_GOAE_Leistungsverzeichnis[Nummer],MATCH(Tabelle5[[#This Row],[GOÄ Nummer]],tbl_GOAE_Leistungsverzeichnis[Mapping ID],0)) -> 206 | I11: =INDEX(tbl_GOAE_Leistungsverzeichnis[Allgemeine Bestimmungen],MATCH(Tabelle5[[#This Row],[GOÄ Nummer]],tbl_GOAE_Leistungsverzeichnis[Mapping ID],0)) -> Wundverbände nach Nummer 200, die im Zusammenhang mit einer operativen Leistung (auch Ätzung, Fremdkörperentfernung), Punktion, Infusion, Transfusion oder Injektion durchgeführt werden, sind Bestandteil dieser Leistung.
A12: 206 | B12: Tapeverband eines kleinen Gelenks | C12: 5 | D12: Min. / Patient | E12: =INDEX(tbl_GOAE_Leistungsverzeichnis[Leistung],MATCH(Tabelle5[[#This Row],[GOÄ Nummer]],tbl_GOAE_Leistungsverzeichnis[Mapping ID],0)) -> Tape-Verband eines kleinen Gelenks | F12: =INDEX(tbl_GOAE_Leistungsverzeichnis[Abschnitt],MATCH(Tabelle5[[#This Row],[GOÄ Nummer]],tbl_GOAE_Leistungsverzeichnis[Mapping ID],0)) -> C. Nichtgebietsbezogene Sonderleistungen | G12: =INDEX(tbl_GOAE_Leistungsverzeichnis[Unterabschnitt (Kategorie)],MATCH(Tabelle5[[#This Row],[GOÄ Nummer]],tbl_GOAE_Leistungsverzeichnis[Mapping ID],0)) -> I. Anlegen von Verbänden | H12: =INDEX(tbl_GOAE_Leistungsverzeichnis[Nummer],MATCH(Tabelle5[[#This Row],[GOÄ Nummer]],tbl_GOAE_Leistungsverzeichnis[Mapping ID],0)) -> 206 | I12: =INDEX(tbl_GOAE_Leistungsverzeichnis[Allgemeine Bestimmungen],MATCH(Tabelle5[[#This Row],[GOÄ Nummer]],tbl_GOAE_Leistungsverzeichnis[Mapping ID],0)) -> Wundverbände nach Nummer 200, die im Zusammenhang mit einer operativen Leistung (auch Ätzung, Fremdkörperentfernung), Punktion, Infusion, Transfusion oder Injektion durchgeführt werden, sind Bestandteil dieser Leistung.
A13: 207 | B13: Tapeverband eines großen Gelenks | C13: 9 | D13: Min. / Patient | E13: =INDEX(tbl_GOAE_Leistungsverzeichnis[Leistung],MATCH(Tabelle5[[#This Row],[GOÄ Nummer]],tbl_GOAE_Leistungsverzeichnis[Mapping ID],0)) -> Tape-Verband eines großen Gelenks oder Zinkleimverband | F13: =INDEX(tbl_GOAE_Leistungsverzeichnis[Abschnitt],MATCH(Tabelle5[[#This Row],[GOÄ Nummer]],tbl_GOAE_Leistungsverzeichnis[Mapping ID],0)) -> C. Nichtgebietsbezogene Sonderleistungen | G13: =INDEX(tbl_GOAE_Leistungsverzeichnis[Unterabschnitt (Kategorie)],MATCH(Tabelle5[[#This Row],[GOÄ Nummer]],tbl_GOAE_Leistungsverzeichnis[Mapping ID],0)) -> I. Anlegen von Verbänden | H13: =INDEX(tbl_GOAE_Leistungsverzeichnis[Nummer],MATCH(Tabelle5[[#This Row],[GOÄ Nummer]],tbl_GOAE_Leistungsverzeichnis[Mapping ID],0)) -> 207 | I13: =INDEX(tbl_GOAE_Leistungsverzeichnis[Allgemeine Bestimmungen],MATCH(Tabelle5[[#This Row],[GOÄ Nummer]],tbl_GOAE_Leistungsverzeichnis[Mapping ID],0)) -> Wundverbände nach Nummer 200, die im Zusammenhang mit einer operativen Leistung (auch Ätzung, Fremdkörperentfernung), Punktion, Infusion, Transfusion oder Injektion durchgeführt werden, sind Bestandteil dieser Leistung.
... A430: 5733 | B430: MRT Zuschlag für Computergestützte Analyse (z.B. Kinetik, 3D-Rekon- struktion) | C430: 8 | D430: Min. / Patient | E430: =INDEX(tbl_GOAE_Leistungsverzeichnis[Leistung],MATCH(Tabelle5[[#This Row],[GOÄ Nummer]],tbl_GOAE_Leistungsverzeichnis[Mapping ID],0)) -> Zuschlag für computergesteuerte Analyse (z.B. Kinetik, 3D-Rekonstruktion) | F430: =INDEX(tbl_GOAE_Leistungsverzeichnis[Abschnitt],MATCH(Tabelle5[[#This Row],[GOÄ Nummer]],tbl_GOAE_Leistungsverzeichnis[Mapping ID],0)) -> O. Strahlendiagnostik, Nuklearmedizin, Magnetresonanztomographie und Strahlentherapie | G430: =INDEX(tbl_GOAE_Leistungsverzeichnis[Unterabschnitt (Kategorie)],MATCH(Tabelle5[[#This Row],[GOÄ Nummer]],tbl_GOAE_Leistungsverzeichnis[Mapping ID],0)) -> 0 | H430: =INDEX(tbl_GOAE_Leistungsverzeichnis[Nummer],MATCH(Tabelle5[[#This Row],[GOÄ Nummer]],tbl_GOAE_Leistungsverzeichnis[Mapping ID],0)) -> 5733 | I430: =INDEX(tbl_GOAE_Leistungsverzeichnis[Allgemeine Bestimmungen],MATCH(Tabelle5[[#This Row],[GOÄ Nummer]],tbl_GOAE_Leistungsverzeichnis[Mapping ID],0)) -> Die Leistungen nach den Nummern 5700 bis 5735 sind je Sitzung jeweils nur einmal berechnungsfähig. Die Nebeneinanderberechnung von Leistungen nach den Nummern 5700 bis 5730 ist in der Rechnung besonders zu begründen. Bei Nebeneinanderberechnung von Leistungen nach den Nummern 5700 bis 5730 ist der Höchstwert nach Nummer 5735 zu beachten.
A431: 200a | B431: Kleiner einfacher Verband | C431: 3 | D431: Min. / Patient | E431: =INDEX(tbl_GOAE_Leistungsverzeichnis[Leistung],MATCH(Tabelle5[[#This Row],[GOÄ Nummer]],tbl_GOAE_Leistungsverzeichnis[Mapping ID],0)) -> #N/A | F431: =INDEX(tbl_GOAE_Leistungsverzeichnis[Abschnitt],MATCH(Tabelle5[[#This Row],[GOÄ Nummer]],tbl_GOAE_Leistungsverzeichnis[Mapping ID],0)) -> #N/A | G431: =INDEX(tbl_GOAE_Leistungsverzeichnis[Unterabschnitt (Kategorie)],MATCH(Tabelle5[[#This Row],[GOÄ Nummer]],tbl_GOAE_Leistungsverzeichnis[Mapping ID],0)) -> #N/A | H431: =INDEX(tbl_GOAE_Leistungsverzeichnis[Nummer],MATCH(Tabelle5[[#This Row],[GOÄ Nummer]],tbl_GOAE_Leistungsverzeichnis[Mapping ID],0)) -> #N/A | I431: =INDEX(tbl_GOAE_Leistungsverzeichnis[Allgemeine Bestimmungen],MATCH(Tabelle5[[#This Row],[GOÄ Nummer]],tbl_GOAE_Leistungsverzeichnis[Mapping ID],0)) -> #N/A
A432: 200b | B432: Großer oder schwieriger Verband | C432: 20 | D432: Min. / Patient | E432: =INDEX(tbl_GOAE_Leistungsverzeichnis[Leistung],MATCH(Tabelle5[[#This Row],[GOÄ Nummer]],tbl_GOAE_Leistungsverzeichnis[Mapping ID],0)) -> #N/A | F432: =INDEX(tbl_GOAE_Leistungsverzeichnis[Abschnitt],MATCH(Tabelle5[[#This Row],[GOÄ Nummer]],tbl_GOAE_Leistungsverzeichnis[Mapping ID],0)) -> #N/A | G432: =INDEX(tbl_GOAE_Leistungsverzeichnis[Unterabschnitt (Kategorie)],MATCH(Tabelle5[[#This Row],[GOÄ Nummer]],tbl_GOAE_Leistungsverzeichnis[Mapping ID],0)) -> #N/A | H432: =INDEX(tbl_GOAE_Leistungsverzeichnis[Nummer],MATCH(Tabelle5[[#This Row],[GOÄ Nummer]],tbl_GOAE_Leistungsverzeichnis[Mapping ID],0)) -> #N/A | I432: =INDEX(tbl_GOAE_Leistungsverzeichnis[Allgemeine Bestimmungen],MATCH(Tabelle5[[#This Row],[GOÄ Nummer]],tbl_GOAE_Leistungsverzeichnis[Mapping ID],0)) -> #N/A
A433: 200c | B433: Binokulus Verband | C433: 3 | D433: Min. / Patient | E433: =INDEX(tbl_GOAE_Leistungsverzeichnis[Leistung],MATCH(Tabelle5[[#This Row],[GOÄ Nummer]],tbl_GOAE_Leistungsverzeichnis[Mapping ID],0)) -> #N/A | F433: =INDEX(tbl_GOAE_Leistungsverzeichnis[Abschnitt],MATCH(Tabelle5[[#This Row],[GOÄ Nummer]],tbl_GOAE_Leistungsverzeichnis[Mapping ID],0)) -> #N/A | G433: =INDEX(tbl_GOAE_Leistungsverzeichnis[Unterabschnitt (Kategorie)],MATCH(Tabelle5[[#This Row],[GOÄ Nummer]],tbl_GOAE_Leistungsverzeichnis[Mapping ID],0)) -> #N/A | H433: =INDEX(tbl_GOAE_Leistungsverzeichnis[Nummer],MATCH(Tabelle5[[#This Row],[GOÄ Nummer]],tbl_GOAE_Leistungsverzeichnis[Mapping ID],0)) -> #N/A | I433: =INDEX(tbl_GOAE_Leistungsverzeichnis[Allgemeine Bestimmungen],MATCH(Tabelle5[[#This Row],[GOÄ Nummer]],tbl_GOAE_Leistungsverzeichnis[Mapping ID],0)) -> #N/A
A434: 200d | B434: Anlegen einer elastischen Binde an einer Extremität | C434: 3 | D434: Min. / Patient | E434: =INDEX(tbl_GOAE_Leistungsverzeichnis[Leistung],MATCH(Tabelle5[[#This Row],[GOÄ Nummer]],tbl_GOAE_Leistungsverzeichnis[Mapping ID],0)) -> #N/A | F434: =INDEX(tbl_GOAE_Leistungsverzeichnis[Abschnitt],MATCH(Tabelle5[[#This Row],[GOÄ Nummer]],tbl_GOAE_Leistungsverzeichnis[Mapping ID],0)) -> #N/A | G434: =INDEX(tbl_GOAE_Leistungsverzeichnis[Unterabschnitt (Kategorie)],MATCH(Tabelle5[[#This Row],[GOÄ Nummer]],tbl_GOAE_Leistungsverzeichnis[Mapping ID],0)) -> #N/A | H434: =INDEX(tbl_GOAE_Leistungsverzeichnis[Nummer],MATCH(Tabelle5[[#This Row],[GOÄ Nummer]],tbl_GOAE_Leistungsverzeichnis[Mapping ID],0)) -> #N/A | I434: =INDEX(tbl_GOAE_Leistungsverzeichnis[Allgemeine Bestimmungen],MATCH(Tabelle5[[#This Row],[GOÄ Nummer]],tbl_GOAE_Leistungsverzeichnis[Mapping ID],0)) -> #N/A
A435: 200e | B435: Anlegen einer redressierenden Kleb-Binde an Hand und/oder Arm | C435: 3 | D435: Min. / Patient | E435: =INDEX(tbl_GOAE_Leistungsverzeichnis[Leistung],MATCH(Tabelle5[[#This Row],[GOÄ Nummer]],tbl_GOAE_Leistungsverzeichnis[Mapping ID],0)) -> #N/A | F435: =INDEX(tbl_GOAE_Leistungsverzeichnis[Abschnitt],MATCH(Tabelle5[[#This Row],[GOÄ Nummer]],tbl_GOAE_Leistungsverzeichnis[Mapping ID],0)) -> #N/A | G435: =INDEX(tbl_GOAE_Leistungsverzeichnis[Unterabschnitt (Kategorie)],MATCH(Tabelle5[[#This Row],[GOÄ Nummer]],tbl_GOAE_Leistungsverzeichnis[Mapping ID],0)) -> #N/A | H435: =INDEX(tbl_GOAE_Leistungsverzeichnis[Nummer],MATCH(Tabelle5[[#This Row],[GOÄ Nummer]],tbl_GOAE_Leistungsverzeichnis[Mapping ID],0)) -> #N/A | I435: =INDEX(tbl_GOAE_Leistungsverzeichnis[Allgemeine Bestimmungen],MATCH(Tabelle5[[#This Row],[GOÄ Nummer]],tbl_GOAE_Leistungsverzeichnis[Mapping ID],0)) -> #N/A
A436: 200f | B436: Anlegen einer Gummi-Elastik-Binde an einer Extremität | C436: 3 | D436: Min. / Patient | E436: =INDEX(tbl_GOAE_Leistungsverzeichnis[Leistung],MATCH(Tabelle5[[#This Row],[GOÄ Nummer]],tbl_GOAE_Leistungsverzeichnis[Mapping ID],0)) -> #N/A | F436: =INDEX(tbl_GOAE_Leistungsverzeichnis[Abschnitt],MATCH(Tabelle5[[#This Row],[GOÄ Nummer]],tbl_GOAE_Leistungsverzeichnis[Mapping ID],0)) -> #N/A | G436: =INDEX(tbl_GOAE_Leistungsverzeichnis[Unterabschnitt (Kategorie)],MATCH(Tabelle5[[#This Row],[GOÄ Nummer]],tbl_GOAE_Leistungsverzeichnis[Mapping ID],0)) -> #N/A | H436: =INDEX(tbl_GOAE_Leistungsverzeichnis[Nummer],MATCH(Tabelle5[[#This Row],[GOÄ Nummer]],tbl_GOAE_Leistungsverzeichnis[Mapping ID],0)) -> #N/A | I436: =INDEX(tbl_GOAE_Leistungsverzeichnis[Allgemeine Bestimmungen],MATCH(Tabelle5[[#This Row],[GOÄ Nummer]],tbl_GOAE_Leistungsverzeichnis[Mapping ID],0)) -> #N/A
A437: 200g | B437: Anlegen eines redressierenden Kleb-Verbandes an den Fuß und/oder Bein | C437: 3 | D437: Min. / Patient | E437: =INDEX(tbl_GOAE_Leistungsverzeichnis[Leistung],MATCH(Tabelle5[[#This Row],[GOÄ Nummer]],tbl_GOAE_Leistungsverzeichnis[Mapping ID],0)) -> #N/A | F437: =INDEX(tbl_GOAE_Leistungsverzeichnis[Abschnitt],MATCH(Tabelle5[[#This Row],[GOÄ Nummer]],tbl_GOAE_Leistungsverzeichnis[Mapping ID],0)) -> #N/A | G437: =INDEX(tbl_GOAE_Leistungsverzeichnis[Unterabschnitt (Kategorie)],MATCH(Tabelle5[[#This Row],[GOÄ Nummer]],tbl_GOAE_Leistungsverzeichnis[Mapping ID],0)) -> #N/A | H437: =INDEX(tbl_GOAE_Leistungsverzeichnis[Nummer],MATCH(Tabelle5[[#This Row],[GOÄ Nummer]],tbl_GOAE_Leistungsverzeichnis[Mapping ID],0)) -> #N/A | I437: =INDEX(tbl_GOAE_Leistungsverzeichnis[Allgemeine Bestimmungen],MATCH(Tabelle5[[#This Row],[GOÄ Nummer]],tbl_GOAE_Leistungsverzeichnis[Mapping ID],0)) -> #N/A
A438: 201a | B438: Redressierender Klebeverband des Brustkorbs oder dachziegelförmiger Klebeverband als TAPE-Verband | C438: 6 | D438: Min. / Patient | E438: =INDEX(tbl_GOAE_Leistungsverzeichnis[Leistung],MATCH(Tabelle5[[#This Row],[GOÄ Nummer]],tbl_GOAE_Leistungsverzeichnis[Mapping ID],0)) -> #N/A | F438: =INDEX(tbl_GOAE_Leistungsverzeichnis[Abschnitt],MATCH(Tabelle5[[#This Row],[GOÄ Nummer]],tbl_GOAE_Leistungsverzeichnis[Mapping ID],0)) -> #N/A | G438: =INDEX(tbl_GOAE_Leistungsverzeichnis[Unterabschnitt (Kategorie)],MATCH(Tabelle5[[#This Row],[GOÄ Nummer]],tbl_GOAE_Leistungsverzeichnis[Mapping ID],0)) -> #N/A | H438: =INDEX(tbl_GOAE_Leistungsverzeichnis[Nummer],MATCH(Tabelle5[[#This Row],[GOÄ Nummer]],tbl_GOAE_Leistungsverzeichnis[Mapping ID],0)) -> #N/A | I438: =INDEX(tbl_GOAE_Leistungsverzeichnis[Allgemeine Bestimmungen],MATCH(Tabelle5[[#This Row],[GOÄ Nummer]],tbl_GOAE_Leistungsverzeichnis[Mapping ID],0)) -> #N/A
A439: 207a | B439: Tape-Verband eines großen Gelenks oder Zinkleimverband | C439: 9 | D439: Min. / Patient | E439: =INDEX(tbl_GOAE_Leistungsverzeichnis[Leistung],MATCH(Tabelle5[[#This Row],[GOÄ Nummer]],tbl_GOAE_Leistungsverzeichnis[Mapping ID],0)) -> #N/A | F439: =INDEX(tbl_GOAE_Leistungsverzeichnis[Abschnitt],MATCH(Tabelle5[[#This Row],[GOÄ Nummer]],tbl_GOAE_Leistungsverzeichnis[Mapping ID],0)) -> #N/A | G439: =INDEX(tbl_GOAE_Leistungsverzeichnis[Unterabschnitt (Kategorie)],MATCH(Tabelle5[[#This Row],[GOÄ Nummer]],tbl_GOAE_Leistungsverzeichnis[Mapping ID],0)) -> #N/A | H439: =INDEX(tbl_GOAE_Leistungsverzeichnis[Nummer],MATCH(Tabelle5[[#This Row],[GOÄ Nummer]],tbl_GOAE_Leistungsverzeichnis[Mapping ID],0)) -> #N/A | I439: =INDEX(tbl_GOAE_Leistungsverzeichnis[Allgemeine Bestimmungen],MATCH(Tabelle5[[#This Row],[GOÄ Nummer]],tbl_GOAE_Leistungsverzeichnis[Mapping ID],0)) -> #N/A
A440: 227a | B440: Gipshülse mit Gelenkschiene bei Verwendung von Kunststoff | C440: 5 | D440: Min. / Patient | E440: =INDEX(tbl_GOAE_Leistungsverzeichnis[Leistung],MATCH(Tabelle5[[#This Row],[GOÄ Nummer]],tbl_GOAE_Leistungsverzeichnis[Mapping ID],0)) -> #N/A | F440: =INDEX(tbl_GOAE_Leistungsverzeichnis[Abschnitt],MATCH(Tabelle5[[#This Row],[GOÄ Nummer]],tbl_GOAE_Leistungsverzeichnis[Mapping ID],0)) -> #N/A | G440: =INDEX(tbl_GOAE_Leistungsverzeichnis[Unterabschnitt (Kategorie)],MATCH(Tabelle5[[#This Row],[GOÄ Nummer]],tbl_GOAE_Leistungsverzeichnis[Mapping ID],0)) -> #N/A | H440: =INDEX(tbl_GOAE_Leistungsverzeichnis[Nummer],MATCH(Tabelle5[[#This Row],[GOÄ Nummer]],tbl_GOAE_Leistungsverzeichnis[Mapping ID],0)) -> #N/A | I440: =INDEX(tbl_GOAE_Leistungsverzeichnis[Allgemeine Bestimmungen],MATCH(Tabelle5[[#This Row],[GOÄ Nummer]],tbl_GOAE_Leistungsverzeichnis[Mapping ID],0)) -> #N/A
A441: 228a | B441: Gipsschienenverband am Unterarm | C441: 13 | D441: Min. / Patient | E441: =INDEX(tbl_GOAE_Leistungsverzeichnis[Leistung],MATCH(Tabelle5[[#This Row],[GOÄ Nummer]],tbl_GOAE_Leistungsverzeichnis[Mapping ID],0)) -> #N/A | F441: =INDEX(tbl_GOAE_Leistungsverzeichnis[Abschnitt],MATCH(Tabelle5[[#This Row],[GOÄ Nummer]],tbl_GOAE_Leistungsverzeichnis[Mapping ID],0)) -> #N/A | G441: =INDEX(tbl_GOAE_Leistungsverzeichnis[Unterabschnitt (Kategorie)],MATCH(Tabelle5[[#This Row],[GOÄ Nummer]],tbl_GOAE_Leistungsverzeichnis[Mapping ID],0)) -> #N/A | H441: =INDEX(tbl_GOAE_Leistungsverzeichnis[Nummer],MATCH(Tabelle5[[#This Row],[GOÄ Nummer]],tbl_GOAE_Leistungsverzeichnis[Mapping ID],0)) -> #N/A | I441: =INDEX(tbl_GOAE_Leistungsverzeichnis[Allgemeine Bestimmungen],MATCH(Tabelle5[[#This Row],[GOÄ Nummer]],tbl_GOAE_Leistungsverzeichnis[Mapping ID],0)) -> #N/A
A442: 228b | B442: Gipsschienenverband am Unterarm bei Verwendung von Kunststoff | C442: 13 | D442: Min. / Patient | E442: =INDEX(tbl_GOAE_Leistungsverzeichnis[Leistung],MATCH(Tabelle5[[#This Row],[GOÄ Nummer]],tbl_GOAE_Leistungsverzeichnis[Mapping ID],0)) -> #N/A | F442: =INDEX(tbl_GOAE_Leistungsverzeichnis[Abschnitt],MATCH(Tabelle5[[#This Row],[GOÄ Nummer]],tbl_GOAE_Leistungsverzeichnis[Mapping ID],0)) -> #N/A | G442: =INDEX(tbl_GOAE_Leistungsverzeichnis[Unterabschnitt (Kategorie)],MATCH(Tabelle5[[#This Row],[GOÄ Nummer]],tbl_GOAE_Leistungsverzeichnis[Mapping ID],0)) -> #N/A | H442: =INDEX(tbl_GOAE_Leistungsverzeichnis[Nummer],MATCH(Tabelle5[[#This Row],[GOÄ Nummer]],tbl_GOAE_Leistungsverzeichnis[Mapping ID],0)) -> #N/A | I442: =INDEX(tbl_GOAE_Leistungsverzeichnis[Allgemeine Bestimmungen],MATCH(Tabelle5[[#This Row],[GOÄ Nummer]],tbl_GOAE_Leistungsverzeichnis[Mapping ID],0)) -> #N/A
... A471: A618 | B471: Lungenfunktionsuntersuchung mit Medikament | C471: 40 | D471: Min. / Patient | E471: =INDEX(tbl_GOAE_Leistungsverzeichnis[Leistung],MATCH(Tabelle5[[#This Row],[GOÄ Nummer]],tbl_GOAE_Leistungsverzeichnis[Mapping ID],0)) -> #N/A | F471: =INDEX(tbl_GOAE_Leistungsverzeichnis[Abschnitt],MATCH(Tabelle5[[#This Row],[GOÄ Nummer]],tbl_GOAE_Leistungsverzeichnis[Mapping ID],0)) -> #N/A | G471: =INDEX(tbl_GOAE_Leistungsverzeichnis[Unterabschnitt (Kategorie)],MATCH(Tabelle5[[#This Row],[GOÄ Nummer]],tbl_GOAE_Leistungsverzeichnis[Mapping ID],0)) -> #N/A | H471: =INDEX(tbl_GOAE_Leistungsverzeichnis[Nummer],MATCH(Tabelle5[[#This Row],[GOÄ Nummer]],tbl_GOAE_Leistungsverzeichnis[Mapping ID],0)) -> #N/A | I471: =INDEX(tbl_GOAE_Leistungsverzeichnis[Allgemeine Bestimmungen],MATCH(Tabelle5[[#This Row],[GOÄ Nummer]],tbl_GOAE_Leistungsverzeichnis[Mapping ID],0)) -> #N/A

Sheet EBM 2026
A1: GOP1) | B1: Kurzlegende | C1: Kalkulationszeit in Minuten2) | D1: Prüfzeit in Minuten | E1: Eignung der Prüfzeit
A2: 1100 | B2: Unvorhergesehene Inanspruchnahme I | C2: KA | D2: ./. | E2: Keine Eignung
A3: 1101 | B3: Unvorhergesehene Inanspruchnahme II | C3: KA | D3: ./. | E3: Keine Eignung
A4: 1102 | B4: Inanspruchnahme an Samstagen | C4: KA | D4: ./. | E4: Keine Eignung
A5: 1205 | B5: Notfallpauschale (Abklärung, Koordination I) | C5: 2 | D5: ./. | E5: Keine Eignung
A6: 1207 | B6: Notfallpauschale (Abklärung, Koordination II) | C6: 2 | D6: ./. | E6: Keine Eignung
A7: 1210 | B7: Notfallpauschale I | C7: KA | D7: ./. | E7: Keine Eignung
A8: 1212 | B8: Notfallpauschale II | C8: KA | D8: ./. | E8: Keine Eignung
A9: 1214 | B9: Notfallkonsultationspauschale I | C9: KA | D9: ./. | E9: Keine Eignung
A10: 1216 | B10: Notfallkonsultationspauschale II | C10: KA | D10: ./. | E10: Keine Eignung
A11: 1218 | B11: Notfallkonsultationspauschale III | C11: KA | D11: ./. | E11: Keine Eignung
A12: 1220 | B12: Reanimationskomplex | C12: KA | D12: ./. | E12: Keine Eignung
A13: 1221 | B13: Zuschlag Beatmung | C13: KA | D13: ./. | E13: Keine Eignung
A14: 1222 | B14: Zuschlag Defibrillation | C14: KA | D14: ./. | E14: Keine Eignung
A15: 1223 | B15: Zuschlag Notfallpauschale zur GOP 01210 | C15: KA | D15: ./. | E15: Keine Eignung
A16: 1224 | B16: Zuschlag Notfallpauschale zur GOP 01212 | C16: KA | D16: ./. | E16: Keine Eignung
A17: 1226 | B17: Zuschlag Notfallpauschale zur GOP 01212 | C17: KA | D17: ./. | E17: Keine Eignung
A18: 01320* | B18: Grundpauschale I für ermächtigte Ärzte, Institute und Krankenhäuser | C18: KA | D18: 6 | E18: Nur Quartalsprofil
A19: 01321* | B19: Grundpauschale II für ermächtigte Ärzte, Institute und Krankenhäuser | C19: KA | D19: 11 | E19: Nur Quartalsprofil
A20: 1322 | B20: Zuschlag TSS-Terminvermittlung oder Hausarztvermittlungsfall | C20: KA | D20: ./. | E20: Keine Eignung
A21: 1323 | B21: Zuschlag TSS-Terminvermittlung oder Hausarztvermittlungsfall | C21: KA | D21: ./. | E21: Keine Eignung
A22: 1410 | B22: Besuch | C22: KA | D22: 13 | E22: Tages- und Quartalsprofil
A23: 1411 | B23: Dringender Besuch I | C23: KA | D23: ./. | E23: Keine Eignung
A24: 1412 | B24: Dringender Besuch II | C24: KA | D24: ./. | E24: Keine Eignung
A25: 1413 | B25: Besuch eines weiteren Kranken | C25: KA | D25: 6 | E25: Tages- und Quartalsprofil
A26: 01414* | B26: Visite auf der Belegstation, je Patient | C26: KA | D26: ./. | E26: Keine Eignung
A27: 1415 | B27: Dringender Besuch eines Patienten in beschützenden Wohnheimen bzw. Einrichtungen | C27: KA | D27: ./. | E27: Keine Eignung
A28: 1416 | B28: Begleitung eines Kranken durch den behandelnden Arzt beim Transport | C28: 10 | D28: 10 | E28: Tages- und Quartalsprofil
A29: 1418 | B29: Besuch im organisierten Not(- fall)dienst | C29: KA | D29: ./. | E29: Keine Eignung
A30: 1420 | B30: Prüfung der Notwendigkeit und Koordination der häuslichen Krankenpflege | C30: KA | D30: 2 | E30: Nur Quartalsprofil
A31: 1422 | B31: Erstverordnung von Behandlungsmaßnahmen zur psychiatrischen häuslichen Krankenpflege | C31: KA | D31: ./. | E31: Keine Eignung
A32: 1424 | B32: Folgeverordnung von Behandlungsmaßnahmen zur psychiatrischen häuslichen Krankenpflege | C32: KA | D32: ./. | E32: Keine Eignung
A33: 1425 | B33: Erstverordnung der spezialisierten ambulanten Palliativversorgung | C33: KA | D33: 15 | E33: Tages- und Quartalsprofil
A34: 1426 | B34: Folgeverordnung zur Fortführung der spezialisierten ambulanten Palliativversorgung | C34: KA | D34: 9 | E34: Tages- und Quartalsprofil
A35: 1430 | B35: Verwaltungskomplex | C35: KA | D35: ./. | E35: Keine Eignung
A36: 1431 | B36: Zusatzpauschale elektronische Patientenakte zu den Gebührenordnungspositionen 01430, 01435 und 01820 | C36: KA | D36: ./. | E36: Keine Eignung
A37: 1435 | B37: Haus-/Fachärztliche Bereitschaftspauschale | C37: KA | D37: ./. | E37: Keine Eignung
A38: 1436 | B38: Konsultationspauschale | C38: KA | D38: ./. | E38: Keine Eignung
A39: 01437* | B39: Grundpauschale für Vertragsärzte, die zur Versorgung gemäß Kapitel 3 bis 11 oder 13 bis 27 zugelassen sind, für bestimmte Auftragsleistungen | C39: KA | D39: ./. | E39: Keine Eignung
A40: 01438* | B40: Telefonische Kontaktaufnahme Telemedizin | C40: KA | D40: ./. | E40: Keine Eignung
A41: 1440 | B41: Verweilen außerhalb der Praxis | C41: 30 | D41: 30 | E41: Tages- und Quartalsprofil
A42: 1442 | B42: Videofallkonferenz mit den an der Versorgung des Patienten beteiligten Pflegefachkräften bzw. Pflegekräften | C42: KA | D42: ./. | E42: Keine Eignung
A43: 1443 | B43: Videofallkonferenz | C43: KA | D43: ./. | E43: Keine Eignung
A44: 1444 | B44: Zuschlag Authentifizierung | C44: KA | D44: ./. | E44: Keine Eignung
A45: 1450 | B45: Zuschlag Videosprechstunde | C45: KA | D45: ./. | E45: Keine Eignung
A46: 1452 | B46: Zuschlag für die strukturierte Versorgung bei Durchführung einer Videosprechstunde | C46: KA | D46: ./. | E46: Keine Eignung | G46: GOP1) | H46: Kurzlegende | I46: Kalkulations- zeit in Minuten2) | J46: Prüfzeit in Minuten | K46: Eignung der Prüfzeit
A47: 1471 | B47: Verlaufskontrolle und Auswertung der DiGA somnio | C47: KA | D47: ./. | E47: Keine Eignung
A48: 1472 | B48: Verlaufskontrolle und Auswertung der DiGA Vivira | C48: KA | D48: ./. | E48: Keine Eignung
A49: 1473 | B49: Verlaufskontrolle und Auswertung der DiGA zanadio | C49: KA | D49: ./. | E49: Keine Eignung
A50: 01474* | B50: Verlaufskontrolle und Auswertung der DiGA Invirto | C50: KA | D50: ./. | E50: Keine Eignung
A51: 1475 | B51: Verlaufskontrolle und Auswertung der DiGA Oviva Direkt für Adipositas | C51: KA | D51: ./. | E51: Keine Eignung
A52: 1476 | B52: Auswahl und/oder Individualisierung von Inhalten der DiGA Mawendo | C52: KA | D52: ./. | E52: Keine Eignung
A53: 1477 | B53: Verlaufskontrolle und Auswertung der DiGA companion patella | C53: KA | D53: ./. | E53: Keine Eignung
A54: 1478 | B54: Verlaufskontrolle und Auswertung der DiGA Kranus Lutera | C54: KA | D54: ./. | E54: Keine Eignung
A55: 01479* | B55: Verlaufskontrolle und Auswertung der DiGA elona therapy Depression | C55: KA | D55: ./. | E55: Keine Eignung
A56: 1480 | B56: Beratung über Organ- und Gewebespenden | C56: 5 | D56: 5 | E56: Tages- und Quartalsprofil
A57: 1481 | B57: Verlaufskontrolle und Auswertung der DiGA ProHerz | C57: KA | D57: ./. | E57: Keine Eignung
A58: 1482 | B58: Verlaufskontrolle und Auswertung der DiGA Kranus Mictera | C58: KA | D58: ./. | E58: Keine Eignung
A59: 1500 | B59: Beobachtung eines Patienten in unmittelbarem Anschluss an eine Leistung gemäß Anhang 8 | C59: 2 | D59: 2 | E59: Tages- und Quartalsprofil
A60: 1501 | B60: Beobachtung und Betreuung eines Patienten in unmittelbarem Anschluss an eine Leistung gemäß Anhang 8 | C60: 5 | D60: 5 | E60: Tages- und Quartalsprofil
A61: 1502 | B61: Zuschlag zu der Gebührenordnungsposition 01500 oder 01501 bei Fortsetzung der Beobachtung und/oder Zusatzpauschale für die weitere Beobachtung gemäß Anhang 8 | C61: 0 | D61: 0 | E61: Tages- und Quartalsprofil
A62: 1503 | B62: Zuschlag zu der Gebührenordnungsposition 01500 oder 01501 bei Fortsetzung der Beobachtung und Betreuung und/oder Zusatzpauschale für die weitere Beobachtung und Betreuung gemäß Anhang 8 | C62: 1 | D62: 1 | E62: Tages- und Quartalsprofil
A63: 01510* | B63: Ambulante Betreuung 2h | C63: 4 | D63: 4 | E63: Tages- und Quartalsprofil
A64: 01511* | B64: Ambulante Betreuung 4h | C64: 6 | D64: 6 | E64: Tages- und Quartalsprofil
A65: 01512* | B65: Ambulante Betreuung 6h | C65: 8 | D65: 8 | E65: Tages- und Quartalsprofil
A66: 01520* | B66: Zusatzpauschale für Beobachtung nach diagnostischer Koronarangiografie | C66: 6 | D66: 6 | E66: Tages- und Quartalsprofil
A67: 01521* | B67: Zusatzpauschale für Beobachtung nach therapeutischer Koronarangiografie | C67: 9 | D67: 9 | E67: Tages- und Quartalsprofil
A68: 01522* | B68: Zusatzpauschale für Beobachtung und Betreuung entsprechend den Inhalten der Vereinbarung zur invasiven Kardiologie gemäß § 135 Abs. 2 SGB V zur Ausführung und Abrechnung invasiver kardiologischer Leistungen | C68: 8 | D68: 8 | E68: Tages- und Quartalsprofil
A69: 01530* | B69: Zusatzpauschale für Beobachtung nach diagnostischer Angiografie | C69: 6 | D69: 6 | E69: Tages- und Quartalsprofil
A70: 01531* | B70: Zusatzpauschale für Beobachtung nach therapeutischer Angiografie | C70: 9 | D70: 9 | E70: Tages- und Quartalsprofil
A71: 01540* | B71: Zusatzpauschale für die Beobachtung und Betreuung eines Kranken unter Behandlung mit Arzneimitteln, einschließlich Infusionen, 2h | C71: 3 | D71: 3 | E71: Tages- und Quartalsprofil
A72: 01541* | B72: Zusatzpauschale für die Beobachtung und Betreuung eines Kranken unter Behandlung mit Arzneimitteln, einschließlich Infusionen, 4h | C72: 4 | D72: 4 | E72: Tages- und Quartalsprofil
A73: 01542* | B73: Zusatzpauschale für die Beobachtung und Betreuung eines Kranken unter Behandlung mit Arzneimitteln, einschließlich Infusionen, 6h | C73: 5 | D73: 5 | E73: Tages- und Quartalsprofil
A74: 01543* | B74: Zusatzpauschale für die Beobachtung und Betreuung eines Kranken unmittelbar nach der Gabe eines Arzneimittels, 2h | C74: 1 | D74: 1 | E74: Tages- und Quartalsprofil
... A76: 01545* | B76: Zusatzpauschale für die Beobachtung und Betreuung eines Kranken unmittelbar nach der Gabe eines Arzneimittels, 6h | C76: 3 | D76: 3 | E76: Tages- und Quartalsprofil
A77: 1546 | B77: Beobachtung und Betreuung bei monoklonaler Antikörpertherapie gegen SARS-CoV-2 | C77: 6 | D77: 4 | E77: Tages- und Quartalsprofil
A78: 1549 | B78: Zusatzpauschale Beobachtung nach intranasaler Anwendung von Esketamin | C78: 4 | D78: 3 | E78: Tages- und Quartalsprofil
A79: 1600 | B79: Ärztlicher Bericht nach Untersuchung | C79: 4 | D79: 1 | E79: Tages- und Quartalsprofil
A80: 1601 | B80: Individueller Arztbrief | C80: 8 | D80: 2 | E80: Tages- und Quartalsprofil
A81: 1602 | B81: Mehrfertigung (z. B. Kopie) eines Berichtes oder Briefes an den Hausarzt | C81: KA | D81: ./. | E81: Keine Eignung
A82: 1610 | B82: Bescheinigung zur Belastungsgrenze | C82: KA | D82: ./. | E82: Keine Eignung
A83: 1611 | B83: Verordnung von medizinischer Rehabilitation | C83: KA | D83: 21 | E83: Tages- und Quartalsprofil
A84: 1612 | B84: Konsiliarbericht vor Psychotherapie | C84: KA | D84: 1 | E84: Tages- und Quartalsprofil
A85: 1613 | B85: Zuschlag geriatrische Rehabilitation | C85: 4 | D85: 3 | E85: Tages- und Quartalsprofil
A86: 1615 | B86: Feststellung und Bescheinigung gemäß Krankenhausbegleitungs- Richtlinie | C86: KA | D86: ./. | E86: Keine Eignung
A87: 1620 | B87: Bescheinigung oder Zeugnis | C87: KA | D87: ./. | E87: Keine Eignung
A88: 1621 | B88: Krankheitsbericht | C88: KA | D88: ./. | E88: Keine Eignung
A89: 1622 | B89: Kurplan, Gutachten, Stellungnahme | C89: KA | D89: ./. | E89: Keine Eignung
A90: 1623 | B90: Kurvorschlag | C90: KA | D90: ./. | E90: Keine Eignung
A91: 1624 | B91: Verordnung medizinischer Vorsorge für Mütter oder Väter | C91: KA | D91: 14 | E91: Tages- und Quartalsprofil
A92: 1626 | B92: Ärztliche Stellungnahme für die Krankenkasse bei der Beantragung einer Genehmigung zur Verordnung von Cannabis | C92: KA | D92: 8 | E92: Tages- und Quartalsprofil
A93: 1630 | B93: Zuschlag für Erstellung eines Medikationsplans | C93: 2 | D93: 2 | E93: Nur Quartalsprofil
A94: 1640 | B94: Zuschlag für die Anlage eines Notfalldatensatzes | C94: KA | D94: ./. | E94: Keine Eignung
A95: 1642 | B95: Löschen eines Notfalldatensatzes | C95: KA | D95: ./. | E95: Keine Eignung
A96: 1643 | B96: Aktualisierung Notfalldatensatz | C96: KA | D96: ./. | E96: Keine Eignung
A97: 1645 | B97: Aufklärung und Beratung sowie Zusammenstellung der Patientenunterlagen gemäß § 6 Abs. 4 der Richtlinie des Gemeinsamen Bundesausschusses zum Zweitmeinungsverfahren | C97: KA | D97: ./. | E97: Keine Eignung
A98: 1647 | B98: Zusatzpauschale ePA- Unterstützungsleistung | C98: 1 | D98: 1 | E98: Nur Quartalsprofil
A99: 1648 | B99: Zusatzpauschale ePA-Erstbefüllung | C99: KA | D99: ./. | E99: Keine Eignung
A100: 1670 | B100: Einholung eines Telekonsiliums | C100: 7 | D100: 6 | E100: Tages- und Quartalsprofil
A101: 1671 | B101: Telekonsiliarische Beurteilung | C101: 10 | D101: 10 | E101: Tages- und Quartalsprofil
...

Sheet TARMED
A1: Kategorie | B1: Nr. | C1: TARMED Bezeichnung | D1: Arztleistung i.e.S. (Min.) | E1: GZF | F1: Vor-Nachbearbeitung (Min.) | G1: Bericht (Min.) | H1: AD gesamt (Min.) | I1: Raumbelegung (Min.) | J1: Wechselzeit (Min.)
A2: Grundleistungen | B2: 00.0010 | C2: Konsultation, erste 5 Min. (Grundkonsultation) | D2: 5 | E2: 1 | H2: 5 | I2: 5
A3: Grundleistungen | B3: 00.0020 | C3: + Konsultation, jede weiteren 5 Min. (Konsultationszuschlag) | D3: 5 | E3: 1 | H3: 5 | I3: 5
A4: Grundleistungen | B4: 00.0030 | C4: + Konsultation, letzte 5 Min. (Konsultationszuschlag) | D4: 5 | E4: 1 | H4: 5 | I4: 5
A5: Grundleistungen | B5: 00.0040 | C5: + Zuschlag für Kinder unter 6 Jahren | D5: 0 | E5: 0 | H5: 0 | I5: 8
A6: Grundleistungen | B6: 00.0050 | C6: Vorbesprechung diagnostischer/therapeutischer Eingriffe mit Patienten/Angehörigen durch den Facharzt, pro 5 Min. | D6: 5 | E6: 1 | H6: 5 | I6: 5
A7: Grundleistungen | B7: 00.0060 | C7: Besuch, erste 5 Min. (Grundbesuch) | D7: 5 | E7: 1 | H7: 5 | I7: 5
A8: Grundleistungen | B8: 00.0070 | C8: + Besuch, jede weiteren 5 Min. (Besuchszuschlag) | D8: 5 | E8: 1 | H8: 5 | I8: 5
A9: Grundleistungen | B9: 00.0080 | C9: + Besuch, letzte 5 Min. (Besuchszuschlag) | D9: 5 | E9: 1 | H9: 5 | I9: 5
A10: Grundleistungen | B10: 00.0095 | C10: + Wegentschädigung, pro 5 Min. | D10: 5 | E10: 1 | H10: 5 | I10: 5
A11: Grundleistungen | B11: 00.0100 | C11: Patiententransport durch den Facharzt, pro 5 Min. | D11: 5 | E11: 1 | H11: 5 | I11: 5
A12: Grundleistungen | B12: 00.0110 | C12: Telefonische Konsultation durch den Facharzt, erste 5 Min. | D12: 5 | E12: 1 | H12: 5 | I12: 5
A13: Grundleistungen | B13: 00.0120 | C13: + Telefonische Konsultation durch den Facharzt, jede wei- teren 5 Min. | D13: 5 | E13: 1 | H13: 5 | I13: 5
... A29: Grundleistungen | B29: 00.0420 | C29: Umfassende Untersuchung durch den Facharzt für Grund- versorgung Medizinische Interpretation: Die Tarifposition beinhaltet die vollständige kleine Unter- suchung durch den Grundversorger sowie mindestens 4 frei wählbare Ergänzungen aus der folgenden Liste oder sämtliche Teile der orientierenden neurologischen Unter- suchung: 1. Ergänzungen ▪ Augeninspektion im auffallenden Licht, Inspek- tion brechende Medien, Fundoskopie (Handoph- thalmoskop) ▪ Visus, Gesichtsfeld (Finger), eventuell Farbsehen und Stereoskopie (Tafeln, Finger) ▪ einfache Gehörprüfung (Flüsterzahlen oder Screening-Audiometrie, eventuell Stimmgabel- tests) ▪ vordere Rhinoskopie oder Otoskopie ▪ neurologische Teiluntersuchung: Zwei Teile der orientierenden oder eine regionale neurologi- sche Untersuchung, z.B. Arm ▪ orientierende Untersuchung des Bewegungsap- parates ▪ physikalische Gefäßuntersuchung inkl. CW-Dopp- leruntersuchung ▪ Lymphknotenstatus, physikalische Untersuchung der Schilddrüse ▪ orientierende externe Genitaluntersuchung ▪ Rektaluntersuchung inkl. Prostatauntersuchung 2. Teile der orientierenden neurologischen Untersuchung ▪ Hirnnerven inkl. kursorischer Gesichtsfeldprü- fung ▪ Spontanmotorik, Muskeltonus, rohe Kraft Extre- mitäten ▪ Sehnenreflexe an Extremitäten, mindestens 4 Paare ▪ Koordinationstests inkl. Gangprüfung ▪ Pyramidenzeichen ▪ Oberflächensensibilität und Tiefensensibilität | D29: 25 | E29: 1 | H29: 25 | I29: 25
A30: Grundleistungen
A31: Grundleistungen | B31: 00.0430 | C31: Kleine rheumatologische Untersuchung durch den Fach- arzt für Rheumatologie, Physikalische Medizin und Rehabi- litation Medizinische Interpretation: Beinhaltet 2 der folgenden Teile: ▪ Gelenkstatus: Palpation, Beweglichkeit aller Ext- remitätengelenke ▪ Wirbelsäulenstatus: Beweglichkeit aller Wirbel- säulensegmente, Palpation der wirbelsäulenna- hen Strukturen ▪ Muskelstatus: Testung von Länge, Kraft; Palpa- tion von Schmerzpunkten an Rumpfmuskeln und Extremitätenmuskeln ▪ 2 oder mehr Teile der orientierenden, neurologi- schen Untersuchung durch den Facharzt für Grundversorgung (00.0420) ▪ internistischer Status: Kardiopulmonale Organe, Abdomen, Gefäße, Lymphknoten | D31: 14 | E31: 1 | H31: 14 | I31: 14
A32: Grundleistungen | B32: 00.0440 | C32: Umfassende rheumatologische Untersuchung durch den Facharzt für Rheumatologie, Physikalische Medizin und Re- habilitation Medizinische Interpretation: Beinhaltet mindestens 3 der folgenden Teile: ▪ Gelenkstatus: Palpation, Beweglichkeit aller Ext- remitätengelenke ▪ Wirbelsäulenstatus: Beweglichkeit aller Wirbel- säulensegmente, Palpation der wirbelsäulenna- hen Strukturen ▪ Muskelstatus: Testung von Länge, Kraft; Palpa- tion von Schmerzpunkten an Rumpfmuskeln und Extremitätenmuskeln ▪ 2 oder mehr Teile der orientierenden, neurologi- schen Untersuchung durch den Facharzt für Grundversorgung (00.0420) ▪ internistischer Status: Kardiopulmonale Organe, Abdomen, Gefäße, Lymphknoten | D32: 25 | E32: 1 | H32: 25 | I32: 25
A33: Grundleistungen | B33: 00.0450 | C33: Spezielle Wachstumsbeurteilung durch den Facharzt für Endokrinologie, Kinder- und Jugendmedizin Medizinische Interpretation: Errechnen der Endgröße bei Verdacht auf Wachstumsstö- rung (Wachstumsverlauf und Knochenalter mit Einbezug der Elterngröße),Erklärung des Ergebnisses sowie Beratung von Eltern und Patient. Exkl. bildgebende Leistungen. | D33: 20 | E33: 1 | H33: 20 | I33: 20
A34: Grundleistungen | B34: 00.0460 | C34: Nachkontrolle des Lebendspenders, als alleinige Leistung | D34: 40 | E34: 1 | H34: 40 | I34: 40
A35: Grundleistungen | B35: 00.0490 | C35: Kognitive Abklärung und Beratung | D35: 60 | E35: 1 | H35: 60 | I35: 60
A36: Grundleistungen | B36: 00.0510 | C36: Spezifische Beratung durch den Facharzt für Grundversor- gung, pro 5 Min. | D36: 5 | E36: 1 | H36: 5 | I36: 5
A37: Grundleistungen | B37: 00.0520 | C37: Psychotherapeutische/psychosoziale Beratung durch den Facharzt für Grundversorgung, pro 5 Min. | D37: 5 | E37: 1 | H37: 5 | I37: 5
A38: Grundleistungen | B38: 00.0525 | C38: Psychosomatische Einzeltherapie, pro 5 Min. Medizinische Interpretation Krisenintervention: ▪ Behandlung bei Suchtverhalten und Suchterkran- kung (psychotrope Substanzen, Alkohol, Nikotin) ▪ Betreuung bei funktionellen/psychosomatischen Leiden, kindlichen/adoleszenten psychischen Entwicklungsstörungen, chronischen psychischen Erkrankungen usw. Am Symptom orientierte Behandlung, auf der Grundlage einer reflektierten, professionell gestalteten Arzt-Patient- Beziehung. Behandelt werden Patienten mit Erkrankungen im ange- stammten somatischen Fachgebiet, deren Gesundheitsstö- rungen wesentlich durch psychische Faktoren verursacht und/oder verstärkt werden. | D38: 5 | E38: 1 | H38: 5 | I38: 5
A39: Grundleistungen
A40: Grundleistungen | B40: 00.0530 | C40: Genetische u/o pränatale Beratung durch den Facharzt, pro 5 Min. | D40: 5 | E40: 1 | H40: 5 | I40: 5
A41: Grundleistungen | B41: 00.0610 | C41: Instruktion von Selbstmessungen, Selbstbehandlungen, durch den Facharzt, pro 5 Min. | D41: 5 | E41: 1 | H41: 5 | I41: 5
A42: Grundleistungen | B42: 00.0710 | C42: Punktion, venös, zwecks Blutentnahme, jede Lokalisation (Bestandteil von 'Allgemeine Grundleistungen') | D42: 0 | E42: 0 | H42: 0 | I42: 0
A43: Grundleistungen | B43: 00.0715 | C43: Punktion, venös, zwecks Blutentnahme, jede Lokalisation durch nichtärztliches Personal | D43: 0 | E43: 0 | H43: 0 | I43: 5
A44: Grundleistungen | B44: 00.0716 | C44: Blutentnahme kapillär, jede Lokalisation durch nichtärztli- ches Personal | D44: 0 | E44: 0 | H44: 0 | I44: 3
A45: Grundleistungen | B45: 00.0720 | C45: Punktion, arteriell, durch den Facharzt (Bestandteil von 'Allgemeine Grundleistungen') | D45: 0 | E45: 0 | H45: 0 | I45: 0
A46: Grundleistungen | B46: 00.0730 | C46: Punktion in Reservoirsystem (intravenös, intraarteriell, Li- quor) durch den Facharzt | D46: 7 | E46: 1 | H46: 7 | I46: 7
A47: Grundleistungen | B47: 00.0740 | C47: Punktion u/o Injektion in Reservoirsystem (Liquor) durch den Facharzt beim Kind/Jugendlichen bis 16 Jahre | D47: 20 | E47: 1 | F47: 9 | H47: 29 | I47: 20
A48: Grundleistungen | B48: 00.0750 | C48: Injektion/Infusion durch nichtärztliches Personal | D48: 0 | E48: 0 | H48: 0 | I48: 5
A49: Grundleistungen | B49: 00.0760 | C49: Injektion, intrakutan/intramukös, durch den Facharzt (Be- standteil von 'Allgemeine Grundleistungen') | D49: 0 | E49: 0 | H49: 0
A50: Grundleistungen | B50: 00.0770 | C50: + Injektion, intrakutan/intramukös, durch den Facharzt, beim Kind bis 7 Jahre | D50: 0 | E50: 0 | H50: 0
A51: Grundleistungen | B51: 00.0780 | C51: Injektion, subkutan (Bestandteil von 'Allgemeine Grund- leistungen') | D51: 0 | E51: 0 | H51: 0
A52: Grundleistungen | B52: 00.0790 | C52: Injektion, intramuskulär (Bestandteil von 'Allgemeine Grundleistungen') | D52: 0 | E52: 0 | H52: 0
A53: Grundleistungen | B53: 00.0800 | C53: Injektion, intravenös (Bestandteil von 'Allgemeine Grund- leistungen') | D53: 0 | E53: 0 | H53: 0
A54: Grundleistungen | B54: 00.0810 | C54: + Injektion, intravenös, beim Kind bis 7 Jahre (Bestandteil von 'Allgemeine Grundleistungen') | D54: 0 | E54: 0 | H54: 0
A55: Grundleistungen | B55: 00.0820 | C55: Injektion, intraarteriell, durch den Facharzt (Bestandteil von 'Allgemeine Grundleistungen') | D55: 0 | E55: 0 | H55: 0
A56: Grundleistungen | B56: 00.0830 | C56: Injektion, intrathekal | D56: 0 | E56: 0 | H56: 0
A57: Grundleistungen | B57: 00.0840 | C57: Injektion in Reservoirsystem (intravenös, intraarteriell, Li- quor) durch den Facharzt | D57: 12 | E57: 1 | H57: 12 | I57: 12
A58: Grundleistungen | B58: 00.0850 | C58: Gefäßzugang, periphervenös, jeder Zugang, durch den Facharzt | D58: 15 | E58: 1 | H58: 15 | I58: 15
A59: Grundleistungen | B59: 00.0855 | C59: Gefäßzugang, periphervenös, jeder Zugang, durch nicht- ärztliches Personal | D59: 0 | E59: 0 | H59: 0 | I59: 15
A60: Grundleistungen | B60: 00.0860 | C60: Gefäßzugang, zentralvenös, jeder Zugang, durch den Fach- arzt | D60: 23 | E60: 1 | H60: 23 | I60: 23
A61: Grundleistungen | B61: 00.0870 | C61: Gefäßzugang, periphervenös beim Neugeborenen | D61: 20 | E61: 1 | H61: 20 | I61: 20
A62: Grundleistungen | B62: 00.0880 | C62: Gefäßzugang, Nabelgefäß | D62: 20 | E62: 1 | H62: 20 | I62: 20
A63: Grundleistungen | B63: 00.0890 | C63: Gefäßzugang, Venaesectio durch den Facharzt beim Kind/Jugendlichen älter als 7 Jahre und Erwachsenen | D63: 16 | E63: 1 | H63: 16 | I63: 16
A64: Grundleistungen | B64: 00.0900 | C64: Gefäßzugang, Venaesectio durch den Facharzt beim Kind bis 7 Jahre | D64: 26 | E64: 1 | H64: 26 | I64: 26
A65: Grundleistungen | B65: 00.0910 | C65: Gefäßzugang, Venaesectio durch den Facharzt bei Frühge- borenen und Neugeborenen | D65: 30 | E65: 1 | H65: 30 | I65: 0
A66: Grundleistungen | B66: 00.0920 | C66: Gefäßzugang, peripherarteriell, durch den Facharzt | D66: 18 | E66: 1 | H66: 18 | I66: 18
A67: Grundleistungen | B67: 00.0930 | C67: Wechsel einer Infusion, venös, durch den Facharzt (Be- standteil von 'Allgemeine Grundleistungen') | D67: 0 | E67: 0 | H67: 0 | I67: 0
A68: Grundleistungen | B68: 00.0940 | C68: Wechsel einer Infusion, arteriell, durch den Facharzt (Be- standteil von 'Allgemeine Grundleistungen') | D68: 0 | E68: 0 | H68: 0 | I68: 0
... A71: Grundleistungen | B71: 00.0970 | C71: Aderlass durch den Facharzt, venös oder arteriell | D71: 11 | E71: 1 | H71: 11 | I71: 11
A72: Grundleistungen | B72: 00.0980 | C72: Einlage eines Port-A-Cath/arteriovenösen Reservoirsys- tems, venös/arteriell, jede Lokalisation der Katheterspitze | D72: 30 | E72: 2 | F72: 9 | H72: 69 | I72: 30
A73: Grundleistungen | B73: 00.0990 | C73: + Einlage eines Port-A-Cath/arteriovenösen Reservoirsys- tems, venös/arteriell, jede Lokalisation der Katheterspitze, beim Kind bis 7 Jahre | D73: 15 | E73: 2 | H73: 30 | I73: 15
A74: Grundleistungen | B74: 00.0995 | C74: Entfernung eines Port-A-Cath/arteriovenösen Reservoir- systems, venös/arteriell, jede Lokalisation der Katheter- spitze | D74: 40 | E74: 2 | F74: 9 | H74: 89 | I74: 40
A75: Grundleistungen | B75: 00.0996 | C75: + Entfernung eines Port-A-Cath/arteriovenösen Reservoir- systems, venös/arteriell, jede Lokalisation der Katheter- spitze, beim Kind bis 7 Jahre | D75: 15 | E75: 2 | H75: 30 | I75: 15
A76: Grundleistungen | B76: 00.1000 | C76: Knochenmarkpunktion, jede Lokalisation | D76: 13 | E76: 1 | F76: 4 | G76: 3 | H76: 20 | I76: 17
A77: Grundleistungen | B77: 00.1010 | C77: + Knochenbiopsie/Knochenentnahme zur histologischen Untersuchung | D77: 5 | E77: 1 | H77: 5 | I77: 5
A78: Grundleistungen | B78: 00.1020 | C78: Feinnadelpunktion zur Entnahme von Gewebe und ande- rem Material | D78: 11 | E78: 1 | H78: 11 | I78: 11
A79: Grundleistungen | B79: 00.1110 | C79: Oberflächenanästhesie mittels Spray/Tropfen: Auge, durch den Facharzt (Bestandteil von 'Allgemeine Grundleis- tungen') | D79: 0 | E79: 0 | H79: 0 | I79: 0
A80: Grundleistungen | B80: 00.1120 | C80: Oberflächenanästhesie mittels Spray/Tropfen: Nase, durch den Facharzt | D80: 1 | E80: 1 | H80: 1 | I80: 1
A81: Grundleistungen | B81: 00.1130 | C81: Oberflächenanästhesie mittels Spray/Tropfen: Mund u/o Rachen, durch den Facharzt | D81: 1 | E81: 1 | H81: 1 | I81: 1
A82: Grundleistungen | B82: 00.1140 | C82: Oberflächenanästhesie mittels Spray/Tropfen: Larynx u/o Hypopharynx, durch den Facharzt | D82: 4 | E82: 1 | H82: 4 | I82: 4
A83: Grundleistungen | B83: 00.1150 | C83: Oberflächenanästhesie mittels Spray/Tropfen: Trommel- fell, inkl. Gehörgang, durch den Facharzt | D83: 5 | E83: 1 | H83: 5 | I83: 5
A84: Grundleistungen | B84: 00.1160 | C84: Oberflächenanästhesie mittels Einlagen, einseitig oder beidseitig, durch den Facharzt | D84: 4 | E84: 1 | H84: 4 | I84: 4
A85: Grundleistungen | B85: 00.1170 | C85: Oberflächenanästhesie, Kryoanästhesie, durch den Fach- arzt | D85: 1 | E85: 1 | H85: 1 | I85: 1
A86: Grundleistungen | B86: 00.1180 | C86: Lokalanästhesie mittels Injektion in Haut / Subkutis / Schleimhaut: Gesicht / Hals / Nacken / Hand, bis 20cm2 | D86: 3 | E86: 1 | H86: 3 | I86: 3
A87: Grundleistungen | B87: 00.1190 | C87: Lokalanästhesie mittels Injektion in Haut / Subkutis / Schleimhaut: übrige Lokalisationen, bis 20 cm2 | D87: 2 | E87: 1 | H87: 2 | I87: 2
A88: Grundleistungen | B88: 00.1200 | C88: Lokalanästhesie mittels Injektion in Haut / Subkutis / Schleimhaut: Gesicht / Hals / Nacken / Hand, 20 bis 40 {cm2} | D88: 5 | E88: 1 | H88: 5 | I88: 5
... A91: Grundleistungen | B91: 00.1230 | C91: Lokalanästhesie mittels Injektion in Haut / Subkutis / | D91: 5 | E91: 1 | H91: 5 | I91: 5
A92: Grundleistungen | C92: Schleimhaut: übrigen Lokalisationen, mehr als 40 {cm2}
A93: Grundleistungen | B93: 00.1240 | C93: Leitungsanästhesie Finger/Zehen, erster Finger/Zehe | D93: 4 | E93: 1 | H93: 4 | I93: 4
A94: Grundleistungen | B94: 00.1250 | C94: + Leitungsanästhesie Finger/Zehen, jede(r) weitere Fin- ger/Zehe | D94: 2 | E94: 1 | H94: 2 | I94: 2
A95: Grundleistungen | B95: 00.1260 | C95: Plexusanästhesie / Regionalanästhesie / Endovenösanäs- thesie durch Nichtanästhesisten (Operateur) | D95: 30 | E95: 1 | H95: 30 | I95: 35
A96: Grundleistungen | B96: 00.1310 | C96: Durchführung und Überwachung einer Desensibilisie- rung/Hyposensibilisierung bei Allergie mittels Injektion durch den Facharzt | D96: 7 | E96: 1 | H96: 7 | I96: 7
A97: Grundleistungen | B97: 00.1320 | C97: Beurteilung des Knochenmarkausstriches durch den Fach- arzt für Hämatologie/Onkologie | D97: 30 | E97: 1 | H97: 30 | I97: 30
A98: Grundleistungen | B98: 00.1325 | C98: Insulintherapie mit Infusionspumpe, pro 5 Min. | D98: 5 | E98: 1 | H98: 5 | I98: 5
A99: Grundleistungen | B99: 00.1330 | C99: Beurteilung des Urinsedimentes durch den Facharzt | D99: 20 | E99: 1 | H99: 20 | I99: 20
A100: Grundleistungen | B100: 00.1345 | C100: Wundtoilette/Verbandwechsel durch nichtärztliches Per- sonal, pro 5 Min. | D100: 0 | E100: 0 | H100: 0 | I100: 5
A101: Grundleistungen | B101: 00.1350 | C101: Verbandwechsel durch den Facharzt nach operativem Wundverschluss (Bestandteil von 'Allgemeine Grundleis- tungen') | D101: 0 | E101: 0 | H101: 0 | I101: 0
A102: Grundleistungen | B102: 00.1360 | C102: Wundtoilette durch den Facharzt (Bestandteil von 'Allge- meine Grundleistungen') | D102: 0 | E102: 0 | H102: 0 | I102: 0
A103: Grundleistungen | B103: 00.1370 | C103: Nachbetreuung/Betreuung/Überwachung in der Arztpra- xis, pro 15 Min. | D103: 2 | E103: 1 | H103: 2 | I103: 15
A104: Grundleistungen | B104: 00.1380 | C104: Reanimation durch den Facharzt außerhalb des Schock- raums, pro 5 Min. | D104: 5 | E104: 1 | H104: 5 | I104: 5
... A121: Grundleistungen | B121: 00.1610 | C121: Behandlung durch den Facharzt für Infektiologie, pro 5 | D121: 5 | E121: 1 | H121: 5 | I121: 5
A122: Grundleistungen | C122: Min.
A123: Grundleistungen | B123: 00.1620 | C123: Behandlung durch den Facharzt für Angiologie, pro 5 Min. | D123: 5 | E123: 1 | H123: 5 | I123: 5
A124: Grundleistungen | B124: 00.1710 | C124: Akupunktur, Konsultation durch den Facharzt, erste 5 Min. | D124: 5 | E124: 1 | H124: 5 | I124: 5
A125: Grundleistungen | B125: 00.1720 | C125: + Akupunktur, Konsultation durch den Facharzt, jede wei- teren 5 Min. | D125: 5 | E125: 1 | H125: 5 | I125: 5
A126: Grundleistungen | B126: 00.1730 | C126: + Akupunktur, Konsultation durch den Facharzt, letzte 5 Min. | D126: 5 | E126: 1 | H126: 5 | I126: 5
A127: Grundleistungen | B127: 00.1735 | C127: + Überwachungszeit Akupunktur, pro 15 Min. | D127: 2 | E127: 1 | H127: 2 | I127: 15
A128: Grundleistungen | B128: 00.1740 | C128: Neuraltherapie, Konsultation durch den Facharzt, erste 5 Min. | D128: 5 | E128: 1 | H128: 5 | I128: 5
A129: Grundleistungen | B129: 00.1750 | C129: + Neuraltherapie, Konsultation durch den Facharzt, jede weiteren 5 Min. | D129: 5 | E129: 1 | H129: 5 | I129: 5
A130: Grundleistungen | B130: 00.1760 | C130: + Neuraltherapie, Konsultation durch den Facharzt, letzte 5 Min. | D130: 5 | E130: 1 | H130: 5 | I130: 5
A131: Grundleistungen | B131: 00.1770 | C131: Homöopathie, Konsultation durch den Facharzt, erste 5 Min. | D131: 5 | E131: 1 | H131: 5 | I131: 5
A132: Grundleistungen | B132: 00.1780 | C132: + Homöopathie, Konsultation durch den Facharzt, jede weiteren 5 Min. | D132: 5 | E132: 1 | H132: 5 | I132: 5
A133: Grundleistungen | B133: 00.1790 | C133: + Homöopathie, Konsultation durch den Facharzt, letzte 5 Min. | D133: 5 | E133: 1 | H133: 5 | I133: 5
A134: Grundleistungen | B134: 00.1800 | C134: + Zuschlag für Repertorisieren, pro 5 Min. | D134: 5 | E134: 1 | H134: 5 | I134: 5
... A209: Verbände | B209: 01.0205 | C209: Thermoplastische härtende Verbände (Schienen) | D209: 5 | E209: 1 | H209: 5 | I209: 15
...

Sheet TARMED Zusatz
A1: Kategorie | B1: Leistungsbeschreibung | C1: Personalbindung in Minuten / Fall
A2: Personalbindung bei speziellen diagnostischen Verfahren | B2: Spezialisierte Diagnostik und Therapie von altersbedingter Makuladegeneration mittels intravitrealer Injektion in den Glaskörper | C2: 232 Min
A3: Personalbindung bei speziellen diagnostischen Verfahren | B3: Spezialisierte Diagnostik und ggf. Entfernung von unklaren Brustherden | C3: 96 Min
A4: Personalbindung bei speziellen diagnostischen Verfahren | B4: Spezialisierte Diagnostik und Therapie von Patienten mit Stimm-, Sprech- und Sprach- störung | C4: 102 Min
A5: Personalbindung bei speziellen diagnostischen Verfahren | B5: Nachsorge nach allogener KM- bzw. SZ-Transplantation | C5: 494 Min
A6: Personalbindung bei speziellen diagnostischen Verfahren | B6: Spezialisierte Diagnostik und Therapie von lymphatischen Systemerkrankungen | C6: 262 Min
A7: Personalbindung bei speziellen diagnostischen Verfahren | B7: Spezialisierte Diagnostik und Therapie von Knochen- und Weichteilsarkomen | C7: 317 Min
A8: Personalbindung bei speziellen diagnostischen Verfahren | B8: Spezialisierte Diagnostik und Therapie von bösartigen Erkrankungen der Hoden oder anderer extragonadaler Gewebe | C8: 250 Min
A9: Personalbindung bei speziellen diagnostischen Verfahren | B9: Spezialisierte Diagnostik und Therapie von rheumatologischen Systemerkrankungen | C9: 101 Min
A10: Personalbindung bei speziellen diagnostischen Verfahren | B10: Spezialisierte Diagnostik und Therapie von Echinokokkose | C10: 126 Min
A11: Personalbindung bei speziellen diagnostischen Verfahren | B11: Spezialisierte Diagnostik und Therapie von Hepatitis C | C11: 165 Min
A12: Personalbindung bei speziellen diagnostischen Verfahren | B12: Spezialisierte Diagnostik und Therapie von Hepatopathie | C12: 183 Min
... A83: Personalbindung in der teilstationären Behandlung | B83: Teilstationäre Behandlung Strahlentherapie | C83: 237 Min/Tag

Sheet GOÄ Leistungskatalog
A1: Abschnitt | B1: Unterabschnitt (Kategorie) | C1: Unterkategorie | D1: Allgemeine Bestimmungen | E1: Mapping ID | F1: Nummer | G1: Leistung | H1: Punktzahl | I1: Gebühr (DM)
A2: B. Grundleistungen und allgemeine Leistungen | B2: I. Allgemeine Beratungen und Untersuchungen | E2: 1 | F2: 1 | G2: Beratung - auch mittels Fernsprecher - | H2: 80 | I2: 9,12
A3: B. Grundleistungen und allgemeine Leistungen | B3: I. Allgemeine Beratungen und Untersuchungen | E3: 2 | F3: 2 | G3: Ausstellung von Wiederholungsrezepten und/oder Überweisungen und/ oder Übermittlung von Befunden oder ärztlichen Anordnungen - auch mittels Fernsprecher - durch die Arzthelferin und/oder Messung von Körperzuständen (z.B. Blutdruck, Temperatur) ohne Beratung, bei einer Inanspruchnahme des Arztes | H3: 30 | I3: 3,42
A4: B. Grundleistungen und allgemeine Leistungen | B4: I. Allgemeine Beratungen und Untersuchungen | E4: 3 | F4: 3 | G4: Eingehende, das gewöhnliche Maß übersteigende Beratung - auch mittels Fernsprecher - | H4: 150 | I4: 17,10
A5: B. Grundleistungen und allgemeine Leistungen | B5: I. Allgemeine Beratungen und Untersuchungen | E5: 4 | F5: 4 | G5: Erhebung der Fremdanamnese über einen Kranken und/oder Unterweisung und Führung der Bezugsperson(en) - im Zusammenhang mit der Behandlung eines Kranken - | H5: 220 | I5: 25,08
A6: B. Grundleistungen und allgemeine Leistungen | B6: I. Allgemeine Beratungen und Untersuchungen | E6: 5 | F6: 5 | G6: Symptombezogene Untersuchung | H6: 80 | I6: 9,12
A7: B. Grundleistungen und allgemeine Leistungen | B7: I. Allgemeine Beratungen und Untersuchungen | E7: 6 | F7: 6 | G7: Vollständige körperliche Untersuchung mindestens eines der folgenden Organsysteme: alle Augenabschnitte, der gesamte HNO-Bereich, das stomatognathe System, die Nieren und ableitenden Harnwege (bei Männern auch gegebenenfalls einschließlich der männlichen Geschlechtsorgane) oder Untersuchung zur Erhebung eines vollständigen Gefäßstatus - gegebenenfalls einschließlich Dokumentation - | H7: 100 | I7: 11,40
A8: B. Grundleistungen und allgemeine Leistungen | B8: I. Allgemeine Beratungen und Untersuchungen | E8: 7 | F8: 7 | G8: Vollständige körperliche Untersuchung mindestens eines der folgenden Organsysteme: das gesamte Hautorgan, die Stütz- und Bewegungsorgane, alle Brustorgane, alle Bauchorgane, der gesamte weibliche Genitaltrakt (gegebenenfalls einschließlich Nieren und ableitende Harnwege) - gegebenenfalls einschließlich Dokumentation - | H8: 160 | I8: 18,24
A9: B. Grundleistungen und allgemeine Leistungen | B9: I. Allgemeine Beratungen und Untersuchungen | E9: 8 | F9: 8 | G9: Untersuchung zur Erhebung des Ganzkörperstatus, gegebenenfalls einschließlich Dokumentation | H9: 260 | I9: 29,64
A10: B. Grundleistungen und allgemeine Leistungen | B10: I. Allgemeine Beratungen und Untersuchungen | E10: 11 | F10: 11 | G10: Digitaluntersuchung des Mastdarms und/oder der Prostata | H10: 60 | I10: 6,84
A11: B. Grundleistungen und allgemeine Leistungen | B11: I. Allgemeine Beratungen und Untersuchungen | E11: 15 | F11: 15 | G11: Einleitung und Koordination flankierender therapeutischer und sozialer Maßnahmen während der kontinuierlichen ambulanten Betreuung eines chronisch Kranken | H11: 300 | I11: 34,20
A12: B. Grundleistungen und allgemeine Leistungen | B12: II. Zuschläge zu Beratungen und Untersuchungen nach Nummer 1, 3, 4, 5, 6, 7 oder 8 | D12: Die Zuschläge nach den Buchstaben A bis D sowie K 1 sind nur mit dem einfachen Gebührensatz berechnungsfähig. Sie dürfen unabhängig von der Anzahl und Kombination der erbrachten Leistungen je Inanspruchnahme des Arztes nur einmal berechnet werden. Neben den Zuschlägen nach den Buchstaben A bis | E12: A | F12: A | G12: Zuschlag für außerhalb der Sprechstunde erbrachte Leistungen | H12: 70 | I12: 7,98
A13: B. Grundleistungen und allgemeine Leistungen | B13: II. Zuschläge zu Beratungen und Untersuchungen nach Nummer 1, 3, 4, 5, 6, 7 oder 8 | D13: Die Zuschläge nach den Buchstaben A bis D sowie K 1 sind nur mit dem einfachen Gebührensatz berechnungsfähig. Sie dürfen unabhängig von der Anzahl und Kombination der erbrachten Leistungen je Inanspruchnahme des Arztes nur einmal berechnet werden. Neben den Zuschlägen nach den Buchstaben A bis | E13: B | F13: B | G13: Zuschlag für in der Zeit zwischen 20 und 22 Uhr oder 6 und 8 Uhr außerhalb der Sprechstunde erbrachte Leistungen | H13: 180 | I13: 20,52
A14: B. Grundleistungen und allgemeine Leistungen | B14: II. Zuschläge zu Beratungen und Untersuchungen nach Nummer 1, 3, 4, 5, 6, 7 oder 8 | D14: Die Zuschläge nach den Buchstaben A bis D sowie K 1 sind nur mit dem einfachen Gebührensatz berechnungsfähig. Sie dürfen unabhängig von der Anzahl und Kombination der erbrachten Leistungen je Inanspruchnahme des Arztes nur einmal berechnet werden. Neben den Zuschlägen nach den Buchstaben A bis | E14: C | F14: C | G14: Zuschlag für in der Zeit zwischen 22 und 6 Uhr erbrachte Leistungen | H14: 320 | I14: 36,48
A15: B. Grundleistungen und allgemeine Leistungen | B15: II. Zuschläge zu Beratungen und Untersuchungen nach Nummer 1, 3, 4, 5, 6, 7 oder 8 | D15: Die Zuschläge nach den Buchstaben A bis D sowie K 1 sind nur mit dem einfachen Gebührensatz berechnungsfähig. Sie dürfen unabhängig von der Anzahl und Kombination der erbrachten Leistungen je Inanspruchnahme des Arztes nur einmal berechnet werden. Neben den Zuschlägen nach den Buchstaben A bis | E15: D | F15: D | G15: Zuschlag für an Samstagen, Sonn- oder Feiertagen erbrachte Leistungen | H15: 220 | I15: 25,08
A16: B. Grundleistungen und allgemeine Leistungen | B16: II. Zuschläge zu Beratungen und Untersuchungen nach Nummer 1, 3, 4, 5, 6, 7 oder 8 | D16: Die Zuschläge nach den Buchstaben A bis D sowie K 1 sind nur mit dem einfachen Gebührensatz berechnungsfähig. Sie dürfen unabhängig von der Anzahl und Kombination der erbrachten Leistungen je Inanspruchnahme des Arztes nur einmal berechnet werden. Neben den Zuschlägen nach den Buchstaben A bis | E16: K1 | F16: K1 | G16: Zuschlag zu Untersuchungen nach Nummer 5, 6, 7 oder 8 bei Kindern bis zum vollendeten 4. Lebensjahr | H16: 120 | I16: 13,68
A17: B. Grundleistungen und allgemeine Leistungen | B17: II. Zuschläge zu Beratungen und Untersuchungen nach Nummer 1, 3, 4, 5, 6, 7 oder 8 | D17: Die Zuschläge nach den Buchstaben A bis D sowie K 1 sind nur mit dem einfachen Gebührensatz berechnungsfähig. Sie dürfen unabhängig von der Anzahl und Kombination der erbrachten Leistungen je Inanspruchnahme des Arztes nur einmal berechnet werden. Neben den Zuschlägen nach den Buchstaben A bis | E17: 20 | F17: 20 | G17: Beratungsgespräch in Gruppen von 4 bis 12 Teilnehmern im Rahmen der Behandlung von chronischen Krankheiten, je Teilnehmer und Sitzung (Dauer mindestens 50 Minuten) | H17: 120 | I17: 13,68
A18: B. Grundleistungen und allgemeine Leistungen | B18: II. Zuschläge zu Beratungen und Untersuchungen nach Nummer 1, 3, 4, 5, 6, 7 oder 8 | D18: Die Zuschläge nach den Buchstaben A bis D sowie K 1 sind nur mit dem einfachen Gebührensatz berechnungsfähig. Sie dürfen unabhängig von der Anzahl und Kombination der erbrachten Leistungen je Inanspruchnahme des Arztes nur einmal berechnet werden. Neben den Zuschlägen nach den Buchstaben A bis | E18: 21 | F18: 21 | G18: Eingehende humangenetische Beratung, je angefangene halbe Stunde und Sitzung | H18: 360 | I18: 41,04
A19: B. Grundleistungen und allgemeine Leistungen | B19: II. Zuschläge zu Beratungen und Untersuchungen nach Nummer 1, 3, 4, 5, 6, 7 oder 8 | D19: Die Zuschläge nach den Buchstaben A bis D sowie K 1 sind nur mit dem einfachen Gebührensatz berechnungsfähig. Sie dürfen unabhängig von der Anzahl und Kombination der erbrachten Leistungen je Inanspruchnahme des Arztes nur einmal berechnet werden. Neben den Zuschlägen nach den Buchstaben A bis | E19: 22 | F19: 22 | G19: Eingehende Beratung einer Schwangeren im Konfliktfall über die Erhaltung oder den Abbruch der Schwangerschaft - auch einschließlich Beratung über soziale Hilfen, gegebenenfalls auch einschließlich Beurteilung über das Vorliegen einer Indikation für einen nicht rechtswidrigen Schwangerschaftsabbruch - | H19: 300 | I19: 34,20
A20: B. Grundleistungen und allgemeine Leistungen | B20: II. Zuschläge zu Beratungen und Untersuchungen nach Nummer 1, 3, 4, 5, 6, 7 oder 8 | D20: Die Zuschläge nach den Buchstaben A bis D sowie K 1 sind nur mit dem einfachen Gebührensatz berechnungsfähig. Sie dürfen unabhängig von der Anzahl und Kombination der erbrachten Leistungen je Inanspruchnahme des Arztes nur einmal berechnet werden. Neben den Zuschlägen nach den Buchstaben A bis | E20: 23 | F20: 23 | G20: Erste Vorsorgeuntersuchung in der Schwangerschaft mit Bestimmung des Geburtstermins - einschließlich Erhebung der Anamnese und Anlegen des Mutterpasses sowie Beratung der Schwangeren über die Mutterschaftsvorsorge, einschließlich Hämoglobinbestimmung - | H20: 300 | I20: 34,20
A21: B. Grundleistungen und allgemeine Leistungen | B21: II. Zuschläge zu Beratungen und Untersuchungen nach Nummer 1, 3, 4, 5, 6, 7 oder 8 | D21: Die Zuschläge nach den Buchstaben A bis D sowie K 1 sind nur mit dem einfachen Gebührensatz berechnungsfähig. Sie dürfen unabhängig von der Anzahl und Kombination der erbrachten Leistungen je Inanspruchnahme des Arztes nur einmal berechnet werden. Neben den Zuschlägen nach den Buchstaben A bis | E21: 24 | F21: 24 | G21: Untersuchung im Schwangerschaftsverlauf -einschließlich Beratung und Bewertung der Befunde, gegebenenfalls auch im Hinblick auf Schwangerschaftsrisiken - | H21: 200 | I21: 22,80
A22: B. Grundleistungen und allgemeine Leistungen | B22: II. Zuschläge zu Beratungen und Untersuchungen nach Nummer 1, 3, 4, 5, 6, 7 oder 8 | D22: Die Zuschläge nach den Buchstaben A bis D sowie K 1 sind nur mit dem einfachen Gebührensatz berechnungsfähig. Sie dürfen unabhängig von der Anzahl und Kombination der erbrachten Leistungen je Inanspruchnahme des Arztes nur einmal berechnet werden. Neben den Zuschlägen nach den Buchstaben A bis | E22: 25 | F22: 25 | G22: Neugeborenen-Erstuntersuchung - gegebenenfalls einschließlich Beratung der Bezugsperson(en) - | H22: 200 | I22: 22,80
A23: B. Grundleistungen und allgemeine Leistungen | B23: II. Zuschläge zu Beratungen und Untersuchungen nach Nummer 1, 3, 4, 5, 6, 7 oder 8 | D23: Die Zuschläge nach den Buchstaben A bis D sowie K 1 sind nur mit dem einfachen Gebührensatz berechnungsfähig. Sie dürfen unabhängig von der Anzahl und Kombination der erbrachten Leistungen je Inanspruchnahme des Arztes nur einmal berechnet werden. Neben den Zuschlägen nach den Buchstaben A bis | E23: 26 | F23: 26 | G23: Untersuchung zur Früherkennung von Krankheiten bei einem Kind bis zum vollendeten 14. Lebensjahr (Erhebung der Anamnese, Feststellung der Körpermaße, Untersuchung von Nervensystem, Sinnesorganen, Skelettsystem, Haut, Brust-, Bauch- und Geschlechtsorganen) - gegebenenfalls einschließlich Beratung der Bezugsperson(en) - | H23: 450 | I23: 51,30
A24: B. Grundleistungen und allgemeine Leistungen | B24: II. Zuschläge zu Beratungen und Untersuchungen nach Nummer 1, 3, 4, 5, 6, 7 oder 8 | D24: Die Zuschläge nach den Buchstaben A bis D sowie K 1 sind nur mit dem einfachen Gebührensatz berechnungsfähig. Sie dürfen unabhängig von der Anzahl und Kombination der erbrachten Leistungen je Inanspruchnahme des Arztes nur einmal berechnet werden. Neben den Zuschlägen nach den Buchstaben A bis | E24: 27 | F24: 27 | G24: Untersuchung einer Frau zur Früherkennung von Krebserkrankungen der Brust, des Genitales, des Rektums und der Haut - einschließlich Erhebung der Anamnese, Abstrichentnahme zur zytologischen Untersuchung, Untersuchung auf Blut im Stuhl und Urinuntersuchung auf Eiweiß, Zucker und Erythrozyten, einschließlich Beratung - | H24: 320 | I24: 36,48
A25: B. Grundleistungen und allgemeine Leistungen | B25: II. Zuschläge zu Beratungen und Untersuchungen nach Nummer 1, 3, 4, 5, 6, 7 oder 8 | D25: Die Zuschläge nach den Buchstaben A bis D sowie K 1 sind nur mit dem einfachen Gebührensatz berechnungsfähig. Sie dürfen unabhängig von der Anzahl und Kombination der erbrachten Leistungen je Inanspruchnahme des Arztes nur einmal berechnet werden. Neben den Zuschlägen nach den Buchstaben A bis | E25: 28 | F25: 28 | G25: Untersuchung eines Mannes zur Früherkennung von Krebserkrankungen des Rektums, der Prostata, des äußeren Genitales und der Haut - einschließlich Erhebung der Anamnese, Urinuntersuchung auf Eiweiß, Zucker und Erythrozyten sowie Untersuchung auf Blut im Stuhl, einschließlich Beratung - | H25: 280 | I25: 31,92
A26: B. Grundleistungen und allgemeine Leistungen | B26: II. Zuschläge zu Beratungen und Untersuchungen nach Nummer 1, 3, 4, 5, 6, 7 oder 8 | D26: Die Zuschläge nach den Buchstaben A bis D sowie K 1 sind nur mit dem einfachen Gebührensatz berechnungsfähig. Sie dürfen unabhängig von der Anzahl und Kombination der erbrachten Leistungen je Inanspruchnahme des Arztes nur einmal berechnet werden. Neben den Zuschlägen nach den Buchstaben A bis | E26: 29 | F26: 29 | G26: Gesundheitsuntersuchung zur Früherkennung von Krankheiten bei einem Erwachsenen - einschließlich Untersuchung zur Erhebung des vollständigen Status (Ganzkörperstatus), Erörterung des individuellen Risikoprofils und verhaltensmedizinischer orientierter Beratung - | H26: 440 | I26: 50,16
A27: B. Grundleistungen und allgemeine Leistungen | B27: II. Zuschläge zu Beratungen und Untersuchungen nach Nummer 1, 3, 4, 5, 6, 7 oder 8 | D27: Die Zuschläge nach den Buchstaben A bis D sowie K 1 sind nur mit dem einfachen Gebührensatz berechnungsfähig. Sie dürfen unabhängig von der Anzahl und Kombination der erbrachten Leistungen je Inanspruchnahme des Arztes nur einmal berechnet werden. Neben den Zuschlägen nach den Buchstaben A bis | E27: 30 | F27: 30 | G27: Erhebung der homöopathischen Erstanamnese mit einer Mindestdauer von einer Stunde nach biographischen und homöopathischindividuellen Gesichtspunkten mit schriftlicher Aufzeichnung zur Einleitung einer homöopathischen Behandlung -einschließlich homöopathischer Repertorisation und Gewichtung der charakteristischen psychischen, allgemeinen und lokalen Zeichen und Symptome des jeweiligen Krankheitsfalls, unter Berücksichtigung der Modalitäten, Alternanzen, Kausal- und Begleitsymptome, zur Auffindung des homöopathischen Einzelmittels, einschließlich Anwendung und Auswertung standardisierter Fragebogen - | H27: 900 | I27: 102,60
A28: B. Grundleistungen und allgemeine Leistungen | B28: II. Zuschläge zu Beratungen und Untersuchungen nach Nummer 1, 3, 4, 5, 6, 7 oder 8 | D28: Die Zuschläge nach den Buchstaben A bis D sowie K 1 sind nur mit dem einfachen Gebührensatz berechnungsfähig. Sie dürfen unabhängig von der Anzahl und Kombination der erbrachten Leistungen je Inanspruchnahme des Arztes nur einmal berechnet werden. Neben den Zuschlägen nach den Buchstaben A bis | E28: 31 | F28: 31 | G28: Homöopathische Folgeanamnese mit einer Mindestdauer von 30 Minuten unter laufender Behandlung nach den Regeln der Einzelmittelhomöopathie zur Beurteilung des Verlaufs und Feststellung des weiteren Vorgehens - einschließlich schriftlicher Aufzeichnungen - | H28: 450 | I28: 51,30
... A31: B. Grundleistungen und allgemeine Leistungen | B31: II. Zuschläge zu Beratungen und Untersuchungen nach Nummer 1, 3, 4, 5, 6, 7 oder 8 | D31: Die Zuschläge nach den Buchstaben A bis D sowie K 1 sind nur mit dem einfachen Gebührensatz berechnungsfähig. Sie dürfen unabhängig von der Anzahl und Kombination der erbrachten Leistungen je Inanspruchnahme des Arztes nur einmal berechnet werden. Neben den Zuschlägen nach den Buchstaben A bis | E31: 34 | F31: 34 | G31: Erörterung (Dauer mindestens 20 Minuten) der Auswirkungen einer Krankheit auf die Lebensgestaltung in unmittelbarem Zusammenhang mit der Feststellung oder erheblichen Verschlimmerung einer nachhaltig lebensverändernden oder lebensbedrohenden Erkrankung - gegebenenfalls einschließlich Planung eines operativen Eingriffs und Abwägung seiner Konsequenzen und Risiken -, einschließlich Beratung - gegebenenfalls unter Einbeziehung von Bezugspersonen - | H31: 300 | I31: 34,20
A32: B. Grundleistungen und allgemeine Leistungen | B32: IV. Visiten, Konsiliartätigkeit, Besuche, Assistenz | E32: 45 | F32: 45 | G32: Visite im Krankenhaus | H32: 70 | I32: 7,98
A33: B. Grundleistungen und allgemeine Leistungen | B33: IV. Visiten, Konsiliartätigkeit, Besuche, Assistenz | E33: 46 | F33: 46 | G33: Zweitvisite im Krankenhaus | H33: 50 | I33: 5,70
A34: B. Grundleistungen und allgemeine Leistungen | B34: IV. Visiten, Konsiliartätigkeit, Besuche, Assistenz | E34: 48 | F34: 48 | G34: Besuch eines Patienten auf einer Pflegestation (z.B. in Alten- oder Pflegeheimen - bei regelmäßiger Tätigkeit des Arztes auf der Pflegestation zu vorher vereinbarten Zeiten - | H34: 120 | I34: 13,68
A35: B. Grundleistungen und allgemeine Leistungen | B35: IV. Visiten, Konsiliartätigkeit, Besuche, Assistenz | E35: 50 | F35: 50 | G35: Besuch, einschließlich Beratung und symptombezogene Untersuchung | H35: 320 | I35: 36,48
A36: B. Grundleistungen und allgemeine Leistungen | B36: IV. Visiten, Konsiliartätigkeit, Besuche, Assistenz | E36: 51 | F36: 51 | G36: Besuch eines weiteren Kranken in derselben häuslichen Gemeinschaft in unmittelbarem zeitlichen Zusammenhang mit der Leistung nach Nummer 50 - einschließlich Beratung und symptombezogener Untersuchung - | H36: 250 | I36: 28,50
A37: B. Grundleistungen und allgemeine Leistungen | B37: IV. Visiten, Konsiliartätigkeit, Besuche, Assistenz | E37: 52 | F37: 52 | G37: Aufsuchen eines Patienten außerhalb der Praxisräume oder des Krankenhauses durch nichtärztliches Personal im Auftrag des niedergelassenen Arztes (z.B. zur Durchführung von kapillaren oder venösen Blutentnahmen, Wundbehandlungen, Verbandwechsel, Katheterwechsel) | H37: 100 | I37: 11,40
A38: B. Grundleistungen und allgemeine Leistungen | B38: IV. Visiten, Konsiliartätigkeit, Besuche, Assistenz | E38: 56 | F38: 56 | G38: Verweilen, ohne Unterbrechung und ohne Erbringung anderer ärztlicher Leistungen -wegen Erkrankung erforderlich -, je angefangene halbe Stunde | H38: 180 | I38: 20,52
A39: B. Grundleistungen und allgemeine Leistungen | B39: IV. Visiten, Konsiliartätigkeit, Besuche, Assistenz | E39: 60 | F39: 60 | G39: Konsiliarische Erörterung zwischen zwei oder mehr liquidationsberechtigten Ärzten, für jeden Arzt | H39: 120 | I39: 13,68
A40: B. Grundleistungen und allgemeine Leistungen | B40: IV. Visiten, Konsiliartätigkeit, Besuche, Assistenz | E40: 61 | F40: 61 | G40: Beistand bei der ärztlichen Leistung eines anderen Arztes (Assistenz), je angefangene halbe Stunde | H40: 130 | I40: 14,82
A41: B. Grundleistungen und allgemeine Leistungen | B41: IV. Visiten, Konsiliartätigkeit, Besuche, Assistenz | E41: 62 | F41: 62 | G41: Zuziehung eines Assistenten bei operativen belegärztlichen Leistungen oder bei ambulanter Operation durch niedergelassene Ärzte, je angefangene halbe Stunde | H41: 150 | I41: 17,10
A42: B. Grundleistungen und allgemeine Leistungen | B42: V. Zuschläge zu den Leistungen nach den Nummern 45 bis 62, 100 und 101 | D42: Die Zuschläge nach den Buchstaben E bis J sowie K 2 sind nur mit dem einfachen Gebührensatz berechnungsfähig. Abweichend hiervon sind die Zuschläge nach den Buchstaben E bis H neben der Leistung nach Nummer 51 nur mit dem halben Gebührensatz berechnungsfähig. Im Zusammenhang mit Leistungen nach den Nummern 45 bis 55 und 60 dürfen die Zuschläge unabhängig von der Anzahl und Kombination der erbrachten Leistungen je Inanspruchnahme des Arztes nur einmal berechnet werden. Im Zusammenhang mit Leistungen nach den Nummern 100 oder 101 dürfen die Zuschläge nach den Buchstaben F bis H unabhängig von der Anzahl und Kombination der erbrachten Leistungen je Inanspruchnahme des Arztes nur einmal berechnet werden. Neben den Zuschlägen nach den Buchstaben E bis J sowie K 2 dürfen die Zuschläge nach den Buchstaben A bis D sowie | E42: E | F42: E | G42: Zuschlag für dringend angeforderte und unverzüglich erfolgte Ausführung | H42: 160 | I42: 18,24
A43: B. Grundleistungen und allgemeine Leistungen | B43: V. Zuschläge zu den Leistungen nach den Nummern 45 bis 62, 100 und 101 | D43: Die Zuschläge nach den Buchstaben E bis J sowie K 2 sind nur mit dem einfachen Gebührensatz berechnungsfähig. Abweichend hiervon sind die Zuschläge nach den Buchstaben E bis H neben der Leistung nach Nummer 51 nur mit dem halben Gebührensatz berechnungsfähig. Im Zusammenhang mit Leistungen nach den Nummern 45 bis 55 und 60 dürfen die Zuschläge unabhängig von der Anzahl und Kombination der erbrachten Leistungen je Inanspruchnahme des Arztes nur einmal berechnet werden. Im Zusammenhang mit Leistungen nach den Nummern 100 oder 101 dürfen die Zuschläge nach den Buchstaben F bis H unabhängig von der Anzahl und Kombination der erbrachten Leistungen je Inanspruchnahme des Arztes nur einmal berechnet werden. Neben den Zuschlägen nach den Buchstaben E bis J sowie K 2 dürfen die Zuschläge nach den Buchstaben A bis D sowie | E43: F | F43: F | G43: Zuschlag für in der Zeit von 20 bis 22 Uhr oder 6 bis 8 Uhr erbrachte Leistungen | H43: 260 | I43: 29,64
A44: B. Grundleistungen und allgemeine Leistungen | B44: V. Zuschläge zu den Leistungen nach den Nummern 45 bis 62, 100 und 101 | D44: Die Zuschläge nach den Buchstaben E bis J sowie K 2 sind nur mit dem einfachen Gebührensatz berechnungsfähig. Abweichend hiervon sind die Zuschläge nach den Buchstaben E bis H neben der Leistung nach Nummer 51 nur mit dem halben Gebührensatz berechnungsfähig. Im Zusammenhang mit Leistungen nach den Nummern 45 bis 55 und 60 dürfen die Zuschläge unabhängig von der Anzahl und Kombination der erbrachten Leistungen je Inanspruchnahme des Arztes nur einmal berechnet werden. Im Zusammenhang mit Leistungen nach den Nummern 100 oder 101 dürfen die Zuschläge nach den Buchstaben F bis H unabhängig von der Anzahl und Kombination der erbrachten Leistungen je Inanspruchnahme des Arztes nur einmal berechnet werden. Neben den Zuschlägen nach den Buchstaben E bis J sowie K 2 dürfen die Zuschläge nach den Buchstaben A bis D sowie | E44: G | F44: G | G44: Zuschlag für in der Zeit zwischen 22 und 6 Uhr erbrachte Leistungen | H44: 450 | I44: 51,30
A45: B. Grundleistungen und allgemeine Leistungen | B45: V. Zuschläge zu den Leistungen nach den Nummern 45 bis 62, 100 und 101 | D45: Die Zuschläge nach den Buchstaben E bis J sowie K 2 sind nur mit dem einfachen Gebührensatz berechnungsfähig. Abweichend hiervon sind die Zuschläge nach den Buchstaben E bis H neben der Leistung nach Nummer 51 nur mit dem halben Gebührensatz berechnungsfähig. Im Zusammenhang mit Leistungen nach den Nummern 45 bis 55 und 60 dürfen die Zuschläge unabhängig von der Anzahl und Kombination der erbrachten Leistungen je Inanspruchnahme des Arztes nur einmal berechnet werden. Im Zusammenhang mit Leistungen nach den Nummern 100 oder 101 dürfen die Zuschläge nach den Buchstaben F bis H unabhängig von der Anzahl und Kombination der erbrachten Leistungen je Inanspruchnahme des Arztes nur einmal berechnet werden. Neben den Zuschlägen nach den Buchstaben E bis J sowie K 2 dürfen die Zuschläge nach den Buchstaben A bis D sowie | E45: H | F45: H | G45: Zuschlag für an Samstagen, Sonn- oder Feiertagen erbrachte Leistungen | H45: 340 | I45: 38,76
A46: B. Grundleistungen und allgemeine Leistungen | B46: V. Zuschläge zu den Leistungen nach den Nummern 45 bis 62, 100 und 101 | D46: Die Zuschläge nach den Buchstaben E bis J sowie K 2 sind nur mit dem einfachen Gebührensatz berechnungsfähig. Abweichend hiervon sind die Zuschläge nach den Buchstaben E bis H neben der Leistung nach Nummer 51 nur mit dem halben Gebührensatz berechnungsfähig. Im Zusammenhang mit Leistungen nach den Nummern 45 bis 55 und 60 dürfen die Zuschläge unabhängig von der Anzahl und Kombination der erbrachten Leistungen je Inanspruchnahme des Arztes nur einmal berechnet werden. Im Zusammenhang mit Leistungen nach den Nummern 100 oder 101 dürfen die Zuschläge nach den Buchstaben F bis H unabhängig von der Anzahl und Kombination der erbrachten Leistungen je Inanspruchnahme des Arztes nur einmal berechnet werden. Neben den Zuschlägen nach den Buchstaben E bis J sowie K 2 dürfen die Zuschläge nach den Buchstaben A bis D sowie | E46: J | F46: J | G46: Zuschlag zur Visite bei Vorhalten eines vom Belegarzt zu vergütenden ärztlichen Bereitschaftsdienstes, je Tag | H46: 80 | I46: 9,12
A47: B. Grundleistungen und allgemeine Leistungen | B47: V. Zuschläge zu den Leistungen nach den Nummern 45 bis 62, 100 und 101 | D47: Die Zuschläge nach den Buchstaben E bis J sowie K 2 sind nur mit dem einfachen Gebührensatz berechnungsfähig. Abweichend hiervon sind die Zuschläge nach den Buchstaben E bis H neben der Leistung nach Nummer 51 nur mit dem halben Gebührensatz berechnungsfähig. Im Zusammenhang mit Leistungen nach den Nummern 45 bis 55 und 60 dürfen die Zuschläge unabhängig von der Anzahl und Kombination der erbrachten Leistungen je Inanspruchnahme des Arztes nur einmal berechnet werden. Im Zusammenhang mit Leistungen nach den Nummern 100 oder 101 dürfen die Zuschläge nach den Buchstaben F bis H unabhängig von der Anzahl und Kombination der erbrachten Leistungen je Inanspruchnahme des Arztes nur einmal berechnet werden. Neben den Zuschlägen nach den Buchstaben E bis J sowie K 2 dürfen die Zuschläge nach den Buchstaben A bis D sowie | E47: K2 | F47: K2 | G47: Zuschlag zu den Leistungen nach Nummer 45, 46, 48, 50, 51, 55 oder 56 bei Kindern bis zum vollendeten 4. Lebensjahr | H47: 120 | I47: 13,68
A48: B. Grundleistungen und allgemeine Leistungen | B48: VI. Berichte, Briefe | E48: 70 | F48: 70 | G48: Kurze Bescheinigung oder kurzes Zeugnis, Arbeitsunfähigkeitsbescheinigung | H48: 40 | I48: 4,56
A49: B. Grundleistungen und allgemeine Leistungen | B49: VI. Berichte, Briefe | E49: 75 | F49: 75 | G49: Ausführlicher schriftlicher Krankheits- und Befundbericht (einschließlich Angaben zur Anamnese, zu dem(n) Befund(en), zur epikritischen Bewertung und gegebenenfalls zur Therapie) | H49: 130 | I49: 14,82
A50: B. Grundleistungen und allgemeine Leistungen | B50: VI. Berichte, Briefe | E50: 76 | F50: 76 | G50: Schriftlicher Diätplan, individuell für den einzelnen Patienten aufgestellt | H50: 70 | I50: 7,98
A51: B. Grundleistungen und allgemeine Leistungen | B51: VI. Berichte, Briefe | E51: 77 | F51: 77 | G51: Schriftliche, individuelle Planung und Leitung einer Kur mit diätetischen, balneologischen und/oder klimatherapeutischen Maßnahmen unter Einbeziehung gesundheitserzieherischer Aspekte | H51: 150 | I51: 17,10
A52: B. Grundleistungen und allgemeine Leistungen | B52: VI. Berichte, Briefe | E52: 78 | F52: 78 | G52: Behandlungsplan für die Chemotherapie und/oder schriftlicher Nachsorgeplan für einen tumorkranken Patienten, individuell für den einzelnen Patienten aufgestellt | H52: 180 | I52: 20,52
A53: B. Grundleistungen und allgemeine Leistungen | B53: VI. Berichte, Briefe | E53: 80 | F53: 80 | G53: Schriftliche gutachtliche Äußerung | H53: 300 | I53: 34,20
A54: B. Grundleistungen und allgemeine Leistungen | B54: VI. Berichte, Briefe | E54: 90 | F54: 90 | G54: Schriftliche Feststellung über das Vorliegen oder Nichtvorliegen einer Indikation für einen Schwangerschaftsabbruch | H54: 120 | I54: 13,68
A55: B. Grundleistungen und allgemeine Leistungen | B55: VI. Berichte, Briefe | E55: 95 | F55: 95 | G55: Schreibgebühr, je angefangene DIN A4-Seite | H55: 60 | I55: 6,84
A56: B. Grundleistungen und allgemeine Leistungen | B56: VI. Berichte, Briefe | E56: 96 | F56: 96 | G56: Schreibgebühr, je Kopie | H56: 3 | I56: 0,34
A57: C. Nichtgebietsbezogene Sonderleistungen | B57: I. Anlegen von Verbänden | D57: Wundverbände nach Nummer 200, die im Zusammenhang mit einer operativen Leistung (auch Ätzung, Fremdkörperentfernung), Punktion, Infusion, Transfusion oder Injektion durchgeführt werden, sind Bestandteil dieser Leistung. | E57: 200 | F57: 200 | G57: Verband - ausgenommen Schnell- und Sprühverbände, Augen-, Ohrenklappen oder Dreiecktücher - | H57: 45 | I57: 5,13
A58: C. Nichtgebietsbezogene Sonderleistungen | B58: I. Anlegen von Verbänden | D58: Wundverbände nach Nummer 200, die im Zusammenhang mit einer operativen Leistung (auch Ätzung, Fremdkörperentfernung), Punktion, Infusion, Transfusion oder Injektion durchgeführt werden, sind Bestandteil dieser Leistung. | E58: 201 | F58: 201 | G58: Redressierender Klebeverband des Brustkorbs oder dachziegelförmiger Klebeverband - ausgenommen Nabelverband - | H58: 65 | I58: 7,41
A59: C. Nichtgebietsbezogene Sonderleistungen | B59: I. Anlegen von Verbänden | D59: Wundverbände nach Nummer 200, die im Zusammenhang mit einer operativen Leistung (auch Ätzung, Fremdkörperentfernung), Punktion, Infusion, Transfusion oder Injektion durchgeführt werden, sind Bestandteil dieser Leistung. | E59: 204 | F59: 204 | G59: Zirkulärer Verband des Kopfes oder des Rumpfes (auch als Wundverband); stabilisierender Verband des Halses, des Schulter- oder Hüftgelenks oder einer Extremität über mindestens zwei große Gelenke; Schanz'scher Halskrawattenverband; Kompressionsverband | H59: 95 | I59: 10,83
A60: C. Nichtgebietsbezogene Sonderleistungen | B60: I. Anlegen von Verbänden | D60: Wundverbände nach Nummer 200, die im Zusammenhang mit einer operativen Leistung (auch Ätzung, Fremdkörperentfernung), Punktion, Infusion, Transfusion oder Injektion durchgeführt werden, sind Bestandteil dieser Leistung. | E60: 206 | F60: 206 | G60: Tape-Verband eines kleinen Gelenks | H60: 70 | I60: 7,98
A61: C. Nichtgebietsbezogene Sonderleistungen | B61: I. Anlegen von Verbänden | D61: Wundverbände nach Nummer 200, die im Zusammenhang mit einer operativen Leistung (auch Ätzung, Fremdkörperentfernung), Punktion, Infusion, Transfusion oder Injektion durchgeführt werden, sind Bestandteil dieser Leistung. | E61: 207 | F61: 207 | G61: Tape-Verband eines großen Gelenks oder Zinkleimverband | H61: 100 | I61: 11,40
A62: C. Nichtgebietsbezogene Sonderleistungen | B62: I. Anlegen von Verbänden | D62: Wundverbände nach Nummer 200, die im Zusammenhang mit einer operativen Leistung (auch Ätzung, Fremdkörperentfernung), Punktion, Infusion, Transfusion oder Injektion durchgeführt werden, sind Bestandteil dieser Leistung. | E62: 208 | F62: 208 | G62: Stärke- oder Gipsfixation, zusätzlich zu einem Verband | H62: 30 | I62: 3,42
A63: C. Nichtgebietsbezogene Sonderleistungen | B63: I. Anlegen von Verbänden | D63: Wundverbände nach Nummer 200, die im Zusammenhang mit einer operativen Leistung (auch Ätzung, Fremdkörperentfernung), Punktion, Infusion, Transfusion oder Injektion durchgeführt werden, sind Bestandteil dieser Leistung. | E63: 209 | F63: 209 | G63: Großflächiges Auftragen von Externa (z.B. Salben, Cremes, Puder, Lotionen, Lösungen) zur Behandlung von Hautkrankheiten mindestens einer Körperregion (Extremität, Kopf, Brust, Bauch, Rücken), je Sitzung | H63: 150 | I63: 17,10
A64: C. Nichtgebietsbezogene Sonderleistungen | B64: I. Anlegen von Verbänden | D64: Wundverbände nach Nummer 200, die im Zusammenhang mit einer operativen Leistung (auch Ätzung, Fremdkörperentfernung), Punktion, Infusion, Transfusion oder Injektion durchgeführt werden, sind Bestandteil dieser Leistung. | E64: 210 | F64: 210 | G64: Kleiner Schienenverband - auch als Notverband bei Frakturen - | H64: 75 | I64: 8,55
A65: C. Nichtgebietsbezogene Sonderleistungen | B65: I. Anlegen von Verbänden | D65: Wundverbände nach Nummer 200, die im Zusammenhang mit einer operativen Leistung (auch Ätzung, Fremdkörperentfernung), Punktion, Infusion, Transfusion oder Injektion durchgeführt werden, sind Bestandteil dieser Leistung. | E65: 211 | F65: 211 | G65: Kleiner Schienenverband - bei Wiederanlegung derselben, gegebenenfalls auch veränderten Schiene - | H65: 60 | I65: 6,84
A66: C. Nichtgebietsbezogene Sonderleistungen | B66: I. Anlegen von Verbänden | D66: Wundverbände nach Nummer 200, die im Zusammenhang mit einer operativen Leistung (auch Ätzung, Fremdkörperentfernung), Punktion, Infusion, Transfusion oder Injektion durchgeführt werden, sind Bestandteil dieser Leistung. | E66: 212 | F66: 212 | G66: Schienenverband mit Einschluß von mindestens zwei großen Gelenken (Schulter-, Ellenbogen-, Hand-, Knie-, Fußgelenk) - auch als Notverband bei Frakturen - | H66: 160 | I66: 18,24
A67: C. Nichtgebietsbezogene Sonderleistungen | B67: I. Anlegen von Verbänden | D67: Wundverbände nach Nummer 200, die im Zusammenhang mit einer operativen Leistung (auch Ätzung, Fremdkörperentfernung), Punktion, Infusion, Transfusion oder Injektion durchgeführt werden, sind Bestandteil dieser Leistung. | E67: 213 | F67: 213 | G67: Schienenverband mit Einschluß von mindestens zwei großen Gelenken (Schulter-, Ellenbogen-, Hand-, Knie-, Fußgelenk) - bei Wiederanlegung derselben, gegebenenfalls auch veränderten Schiene - | H67: 100 | I67: 11,40
A68: C. Nichtgebietsbezogene Sonderleistungen | B68: I. Anlegen von Verbänden | D68: Wundverbände nach Nummer 200, die im Zusammenhang mit einer operativen Leistung (auch Ätzung, Fremdkörperentfernung), Punktion, Infusion, Transfusion oder Injektion durchgeführt werden, sind Bestandteil dieser Leistung. | E68: 214 | F68: 214 | G68: Abduktionsschienenverband - auch mit Stärke- oder Gipsfixation - | H68: 240 | I68: 27,36
... A124: C. Nichtgebietsbezogene Sonderleistungen | B124: II. Blutentnahmen, Injektionen, Infiltrationen, Infusionen, Transfusionen, Implantation, Abstrichentnahmen | D124: Die Leistungen nach den Nummern 252 bis 258 und 261 sind nicht mehrfach berechnungsfähig, wenn anstelle einer Mischung mehrere Arzneimittel bei liegender Kanüle im zeitlichen Zusammenhang nacheinander verabreicht werden. Die Leistungen nach den Nummern 270, 273 bis 281, 283, 286 sowie 287 können jeweils nur einmal je Behandlungstag berechnet werden. Die Leistungen nach Nummer 271 oder 272 sind je Gefäßzugang einmal, insgesamt jedoch nicht mehr als zweimal je Behandlungstag berechnungsfähig. Die zweimalige Berechnung der Leistungen nach den Nummern 271 oder 272 setzt gesonderte Punktionen verschiedener Blutgefäße voraus. Gegebenenfalls erforderliche Gefäßpunktionen sind Bestandteil der Leistungen nach den Nummern 270 bis 287 und mit den Gebühren abgegolten. Die Leistungen nach den Nummern 271 bis 276 sind nicht nebeneinander berechnungsfähig. | E124: 400 | F124: 400 | G124: Milliliter) zur späteren Retransfusion bei Aufbewahrung als Vollblutkonserve - gegebenenfalls einschließlich Konservierung - | H124: 230 | I124: 26,22
A125: C. Nichtgebietsbezogene Sonderleistungen | B125: II. Blutentnahmen, Injektionen, Infiltrationen, Infusionen, Transfusionen, Implantation, Abstrichentnahmen | D125: Die Leistungen nach den Nummern 252 bis 258 und 261 sind nicht mehrfach berechnungsfähig, wenn anstelle einer Mischung mehrere Arzneimittel bei liegender Kanüle im zeitlichen Zusammenhang nacheinander verabreicht werden. Die Leistungen nach den Nummern 270, 273 bis 281, 283, 286 sowie 287 können jeweils nur einmal je Behandlungstag berechnet werden. Die Leistungen nach Nummer 271 oder 272 sind je Gefäßzugang einmal, insgesamt jedoch nicht mehr als zweimal je Behandlungstag berechnungsfähig. Die zweimalige Berechnung der Leistungen nach den Nummern 271 oder 272 setzt gesonderte Punktionen verschiedener Blutgefäße voraus. Gegebenenfalls erforderliche Gefäßpunktionen sind Bestandteil der Leistungen nach den Nummern 270 bis 287 und mit den Gebühren abgegolten. Die Leistungen nach den Nummern 271 bis 276 sind nicht nebeneinander berechnungsfähig. | E125: C | F125: C | G125: bis +6 Grad C sowie Schockgefrieren des Frischplasmas und anschließender Aufbewahrung bei -30 Grad C oder darunter - | H125: 350 | I125: 39,90
A126: C. Nichtgebietsbezogene Sonderleistungen | B126: II. Blutentnahmen, Injektionen, Infiltrationen, Infusionen, Transfusionen, Implantation, Abstrichentnahmen | D126: Die Leistungen nach den Nummern 252 bis 258 und 261 sind nicht mehrfach berechnungsfähig, wenn anstelle einer Mischung mehrere Arzneimittel bei liegender Kanüle im zeitlichen Zusammenhang nacheinander verabreicht werden. Die Leistungen nach den Nummern 270, 273 bis 281, 283, 286 sowie 287 können jeweils nur einmal je Behandlungstag berechnet werden. Die Leistungen nach Nummer 271 oder 272 sind je Gefäßzugang einmal, insgesamt jedoch nicht mehr als zweimal je Behandlungstag berechnungsfähig. Die zweimalige Berechnung der Leistungen nach den Nummern 271 oder 272 setzt gesonderte Punktionen verschiedener Blutgefäße voraus. Gegebenenfalls erforderliche Gefäßpunktionen sind Bestandteil der Leistungen nach den Nummern 270 bis 287 und mit den Gebühren abgegolten. Die Leistungen nach den Nummern 271 bis 276 sind nicht nebeneinander berechnungsfähig. | E126: 290 | F126: 290 | G126: Infiltration gewebehärtender Mittel | H126: 120 | I126: 13,68
A127: C. Nichtgebietsbezogene Sonderleistungen | B127: II. Blutentnahmen, Injektionen, Infiltrationen, Infusionen, Transfusionen, Implantation, Abstrichentnahmen | D127: Die Leistungen nach den Nummern 252 bis 258 und 261 sind nicht mehrfach berechnungsfähig, wenn anstelle einer Mischung mehrere Arzneimittel bei liegender Kanüle im zeitlichen Zusammenhang nacheinander verabreicht werden. Die Leistungen nach den Nummern 270, 273 bis 281, 283, 286 sowie 287 können jeweils nur einmal je Behandlungstag berechnet werden. Die Leistungen nach Nummer 271 oder 272 sind je Gefäßzugang einmal, insgesamt jedoch nicht mehr als zweimal je Behandlungstag berechnungsfähig. Die zweimalige Berechnung der Leistungen nach den Nummern 271 oder 272 setzt gesonderte Punktionen verschiedener Blutgefäße voraus. Gegebenenfalls erforderliche Gefäßpunktionen sind Bestandteil der Leistungen nach den Nummern 270 bis 287 und mit den Gebühren abgegolten. Die Leistungen nach den Nummern 271 bis 276 sind nicht nebeneinander berechnungsfähig. | E127: 291 | F127: 291 | G127: Implantation von Hormonpreßlingen | H127: 70 | I127: 7,98
A128: C. Nichtgebietsbezogene Sonderleistungen | B128: II. Blutentnahmen, Injektionen, Infiltrationen, Infusionen, Transfusionen, Implantation, Abstrichentnahmen | D128: Die Leistungen nach den Nummern 252 bis 258 und 261 sind nicht mehrfach berechnungsfähig, wenn anstelle einer Mischung mehrere Arzneimittel bei liegender Kanüle im zeitlichen Zusammenhang nacheinander verabreicht werden. Die Leistungen nach den Nummern 270, 273 bis 281, 283, 286 sowie 287 können jeweils nur einmal je Behandlungstag berechnet werden. Die Leistungen nach Nummer 271 oder 272 sind je Gefäßzugang einmal, insgesamt jedoch nicht mehr als zweimal je Behandlungstag berechnungsfähig. Die zweimalige Berechnung der Leistungen nach den Nummern 271 oder 272 setzt gesonderte Punktionen verschiedener Blutgefäße voraus. Gegebenenfalls erforderliche Gefäßpunktionen sind Bestandteil der Leistungen nach den Nummern 270 bis 287 und mit den Gebühren abgegolten. Die Leistungen nach den Nummern 271 bis 276 sind nicht nebeneinander berechnungsfähig. | E128: 297 | F128: 297 | G128: Entnahme und Aufbereitung von Abstrichmaterial zur zytologischen Untersuchung - gegebenenfalls einschließlich Fixierung - | H128: 45 | I128: 5,13
A129: C. Nichtgebietsbezogene Sonderleistungen | B129: II. Blutentnahmen, Injektionen, Infiltrationen, Infusionen, Transfusionen, Implantation, Abstrichentnahmen | D129: Die Leistungen nach den Nummern 252 bis 258 und 261 sind nicht mehrfach berechnungsfähig, wenn anstelle einer Mischung mehrere Arzneimittel bei liegender Kanüle im zeitlichen Zusammenhang nacheinander verabreicht werden. Die Leistungen nach den Nummern 270, 273 bis 281, 283, 286 sowie 287 können jeweils nur einmal je Behandlungstag berechnet werden. Die Leistungen nach Nummer 271 oder 272 sind je Gefäßzugang einmal, insgesamt jedoch nicht mehr als zweimal je Behandlungstag berechnungsfähig. Die zweimalige Berechnung der Leistungen nach den Nummern 271 oder 272 setzt gesonderte Punktionen verschiedener Blutgefäße voraus. Gegebenenfalls erforderliche Gefäßpunktionen sind Bestandteil der Leistungen nach den Nummern 270 bis 287 und mit den Gebühren abgegolten. Die Leistungen nach den Nummern 271 bis 276 sind nicht nebeneinander berechnungsfähig. | E129: 298 | F129: 298 | G129: Entnahme und gegebenenfalls Aufbereitung von Abstrichmaterial zur mikrobiologischen Untersuchung - gegebenenfalls einschließlich Fixierung - | H129: 40 | I129: 4,56
A130: C. Nichtgebietsbezogene Sonderleistungen | B130: II. Blutentnahmen, Injektionen, Infiltrationen, Infusionen, Transfusionen, Implantation, Abstrichentnahmen | D130: Zum Inhalt der Leistungen für Punktionen gehören die damit im Zusammenhang stehenden Injektionen, Instillationen, Spülungen sowie Entnahmen z.B. von Blut, Liquor, Gewebe. | E130: 300 | F130: 300 | G130: Punktion eines Gelenks | H130: 120 | I130: 13,68
A131: C. Nichtgebietsbezogene Sonderleistungen | B131: II. Blutentnahmen, Injektionen, Infiltrationen, Infusionen, Transfusionen, Implantation, Abstrichentnahmen | D131: Zum Inhalt der Leistungen für Punktionen gehören die damit im Zusammenhang stehenden Injektionen, Instillationen, Spülungen sowie Entnahmen z.B. von Blut, Liquor, Gewebe. | E131: 301 | F131: 301 | G131: Punktion eines Ellenbogen-, Knie- oder Wirbelgelenks | H131: 160 | I131: 18,24
A132: C. Nichtgebietsbezogene Sonderleistungen | B132: II. Blutentnahmen, Injektionen, Infiltrationen, Infusionen, Transfusionen, Implantation, Abstrichentnahmen | D132: Zum Inhalt der Leistungen für Punktionen gehören die damit im Zusammenhang stehenden Injektionen, Instillationen, Spülungen sowie Entnahmen z.B. von Blut, Liquor, Gewebe. | E132: 302 | F132: 302 | G132: Punktion eines Schulter- oder Hüftgelenks | H132: 250 | I132: 28,50
A133: C. Nichtgebietsbezogene Sonderleistungen | B133: II. Blutentnahmen, Injektionen, Infiltrationen, Infusionen, Transfusionen, Implantation, Abstrichentnahmen | D133: Zum Inhalt der Leistungen für Punktionen gehören die damit im Zusammenhang stehenden Injektionen, Instillationen, Spülungen sowie Entnahmen z.B. von Blut, Liquor, Gewebe. | E133: 303 | F133: 303 | G133: Punktion einer Drüse, eines Schleimbeutels, Ganglions, Seroms, Hygroms, Hämatoms oder Abszesses oder oberflächiger Körperteile | H133: 80 | I133: 9,12
A134: C. Nichtgebietsbezogene Sonderleistungen | B134: II. Blutentnahmen, Injektionen, Infiltrationen, Infusionen, Transfusionen, Implantation, Abstrichentnahmen | D134: Zum Inhalt der Leistungen für Punktionen gehören die damit im Zusammenhang stehenden Injektionen, Instillationen, Spülungen sowie Entnahmen z.B. von Blut, Liquor, Gewebe. | E134: 304 | F134: 304 | G134: Punktion der Augenhöhle | H134: 160 | I134: 18,24
A135: C. Nichtgebietsbezogene Sonderleistungen | B135: II. Blutentnahmen, Injektionen, Infiltrationen, Infusionen, Transfusionen, Implantation, Abstrichentnahmen | D135: Zum Inhalt der Leistungen für Punktionen gehören die damit im Zusammenhang stehenden Injektionen, Instillationen, Spülungen sowie Entnahmen z.B. von Blut, Liquor, Gewebe. | E135: 305 | F135: 305 | G135: Punktion der Liquorräume (Subokzipital- oder Lumbalpunktion) | H135: 350 | I135: 39,90
A136: C. Nichtgebietsbezogene Sonderleistungen | B136: II. Blutentnahmen, Injektionen, Infiltrationen, Infusionen, Transfusionen, Implantation, Abstrichentnahmen | D136: Zum Inhalt der Leistungen für Punktionen gehören die damit im Zusammenhang stehenden Injektionen, Instillationen, Spülungen sowie Entnahmen z.B. von Blut, Liquor, Gewebe. | E136: 307 | F136: 307 | G136: Punktion des Pleuraraums oder der Bauchhöhle | H136: 250 | I136: 28,50
A137: C. Nichtgebietsbezogene Sonderleistungen | B137: II. Blutentnahmen, Injektionen, Infiltrationen, Infusionen, Transfusionen, Implantation, Abstrichentnahmen | D137: Zum Inhalt der Leistungen für Punktionen gehören die damit im Zusammenhang stehenden Injektionen, Instillationen, Spülungen sowie Entnahmen z.B. von Blut, Liquor, Gewebe. | E137: 308 | F137: 308 | G137: Gewebeentnahme aus der Pleura - gegebenenfalls einschließlich Punktion - | H137: 350 | I137: 39,90
... A201: C. Nichtgebietsbezogene Sonderleistungen | B201: VI. Sonographische Leistungen | D201: 1. Die Zuschläge nach den Nummern 401 sowie 404 bis 406 sind nur mit dem einfachen Gebührensatz berechnungsfähig. 2. Die Zuschläge bzw. Leistungen nach den Nummern 401 bis 418 sowie 422 bis 424 sind je Sitzung jeweils nur einmal berechnungsfähig. 3. Die Zuschläge bzw. Leistungen nach den Nummern 410 bis 418 sind nicht nebeneinander berechnungsfähig. 4. Die Leistungen nach den Nummern 422 bis 424 sind nicht nebeneinander berechnungsfähig. 5. Mit den Gebühren für die Zuschläge bzw. Leistungen nach den Nummern 401 bis 424 ist die erforderliche Bilddokumentation abgegolten. 6. Als Organe im Sinne der Leistungen nach den Nummern 410 und 420 gelten neben den anatomisch definierten Organen auch der Darm, Gelenke als Funktionseinheiten sowie Muskelgruppen, Lymphknoten und/oder Gefäße einer Körperregion. Als Organ gilt die jeweils untersuchte Körperregion unabhängig davon, ob nur Gefäße oder nur Lymphknoten oder Gefäße und Lymphknoten bzw. Weichteile untersucht werden. Die Darstellung des Darms gilt als eine Organuntersuchung unabhängig davon, ob der gesamte Darm, mehrere Darmabschnitte oder nur ein einziger Darmabschnitt untersucht werden. 7. Die sonographische Untersuchung eines Organs erfordert die Differenzierung der Organstrukturen in mindestens zwei Ebenen und schließt gegebenenfalls die Untersuchung unterschiedlicher Funktionszustände und die mit der gezielten Organuntersuchung verbundene Darstellung von Nachbarorganen mit ein. | E201: 424 | F201: 424 | G201: Zweidimensionale doppler-echokardiographische Untersuchung mit Bilddokumentation -einschließlich der Leistung nach Nummer 423 - (Duplex-Verfahren) | H201: 700 | I201: 79,80
A202: C. Nichtgebietsbezogene Sonderleistungen | B202: VII. Intensivmedizinische und sonstige Leistungen | E202: 427 | F202: 427 | G202: Assistierte und/oder kontrollierte apparative Beatmung durch Saug- Druck-Verfahren bei vitaler Indikation, bis zu 12 Stunden Dauer | H202: 150 | I202: 17,10
A203: C. Nichtgebietsbezogene Sonderleistungen | B203: VII. Intensivmedizinische und sonstige Leistungen | E203: 428 | F203: 428 | G203: Assistierte und/oder kontrollierte apparative Beatmung durch Saug- Druck-Verfahren bei vitaler Indikation, bei mehr als 12 Stunden Dauer, je Tag | H203: 220 | I203: 25,08
A204: C. Nichtgebietsbezogene Sonderleistungen | B204: VII. Intensivmedizinische und sonstige Leistungen | E204: 429 | F204: 429 | G204: Wiederbelebungsversuch - einschließlich künstlicher Beatmung und extrathorakaler indirekter Herzmassage, gegebenenfalls einschließlich Intubation - | H204: 400 | I204: 45,60
A205: C. Nichtgebietsbezogene Sonderleistungen | B205: VII. Intensivmedizinische und sonstige Leistungen | E205: 430 | F205: 430 | G205: Extra- oder intrathorakale Elektro-Defibrillation und/oder -Stimulation des Herzens | H205: 400 | I205: 45,60
A206: C. Nichtgebietsbezogene Sonderleistungen | B206: VII. Intensivmedizinische und sonstige Leistungen | E206: 431 | F206: 431 | G206: Elektrokardioskopie im Notfall | H206: 100 | I206: 11,40
A207: C. Nichtgebietsbezogene Sonderleistungen | B207: VII. Intensivmedizinische und sonstige Leistungen | E207: 433 | F207: 433 | G207: Ausspülung des Magens - auch mit Sondierung der Speiseröhre und des Magens und/oder Spülung des Duodenums - | H207: 140 | I207: 15,96
A208: C. Nichtgebietsbezogene Sonderleistungen | B208: VII. Intensivmedizinische und sonstige Leistungen | E208: 435 | F208: 435 | G208: Stationäre intensivmedizinische Überwachung und Behandlung eines Patienten auf einer dafür eingerichteten gesonderten Betteneinheit eines Krankenhauses mit spezieller Personal-und Geräteausstattung - einschließlich aller im Rahmen der Intensivbehandlung erbrachten Leistungen, soweit deren Berechnungsfähigkeit nachfolgend ausgeschlossen ist -, bis zu 24 Stunden Dauer | H208: 900 | I208: 102,60
A209: C. Nichtgebietsbezogene Sonderleistungen | B209: VII. Intensivmedizinische und sonstige Leistungen | E209: 440 | F209: 440 | G209: Zuschlag für die Anwendung eines Operationsmikroskops bei ambulanten operativen Leistungen | H209: 400 | I209: 45,60
A210: C. Nichtgebietsbezogene Sonderleistungen | B210: VII. Intensivmedizinische und sonstige Leistungen | E210: 442 | F210: 442 | G210: Zuschlag bei ambulanter Durchführung von operativen Leistungen, die mit Punktzahlen von 250 bis 499 Punkten bewertet sind | H210: 400 | I210: 45,60
A211: C. Nichtgebietsbezogene Sonderleistungen | B211: VII. Intensivmedizinische und sonstige Leistungen | E211: 443 | F211: 443 | G211: Zuschlag bei ambulanter Durchführung von operativen Leistungen, die mit Punktzahlen von 500 bis 799 Punkten bewertet sind | H211: 750 | I211: 85,50
A212: C. Nichtgebietsbezogene Sonderleistungen | B212: VII. Intensivmedizinische und sonstige Leistungen | E212: 444 | F212: 444 | G212: Zuschlag bei ambulanter Durchführung von operativen Leistungen, die mit Punktzahlen von 800 bis 1199 Punkten bewertet sind | H212: 1300 | I212: 148,20
A213: C. Nichtgebietsbezogene Sonderleistungen | B213: VII. Intensivmedizinische und sonstige Leistungen | E213: 445 | F213: 445 | G213: Zuschlag bei ambulanter Durchführung von operativen Leistungen, die mit Punktzahlen von 1200 und mehr Punkten bewertet sind | H213: 2200 | I213: 250,80
... A217: C. Nichtgebietsbezogene Sonderleistungen | B217: VII. Intensivmedizinische und sonstige Leistungen | E217: 449 | F217: 449 | G217: Beobachtung und Betreuung eines Kranken über mehr als vier Stunden während der Aufwach- und/oder Erholungszeit bis zum Eintritt der Transportfähigkeit nach zuschlagsberechtigten ambulanten operativen Leistungen bei Durchführung unter zuschlagsberechtigten ambulanten Anästhesien bzw. Narkosen | H217: 900 | I217: 102,60
A218: D. Anästhesieleistungen | E218: 450 | F218: 450 | G218: Rauschnarkose - auch mit Lachgas - | H218: 76 | I218: 8,66
A219: D. Anästhesieleistungen | E219: 451 | F219: 451 | G219: Intravenöse Kurznarkose | H219: 121 | I219: 13,79
A220: D. Anästhesieleistungen | E220: 452 | F220: 452 | G220: Intravenöse Narkose (mehrmalige Verabreichung des Narkotikums) | H220: 190 | I220: 21,66
A221: D. Anästhesieleistungen | E221: 453 | F221: 453 | G221: Vollnarkose | H221: 210 | I221: 23,94
A222: D. Anästhesieleistungen | E222: 460 | F222: 460 | G222: Kombinationsnarkose mit Maske, Gerät - auch Insufflationsnarkose -, bis zu einer Stunde | H222: 404 | I222: 46,06
A223: D. Anästhesieleistungen | E223: 461 | F223: 461 | G223: Kombinationsnarkose mit Maske, Gerät - auch Insufflationsnarkose -, jede weitere angefangene halbe Stunde | H223: 202 | I223: 23,03
...
